{
  "chunk": 5,
  "count": 50,
  "generated_at": "2026-03-29T05:16:53Z",
  "items": [
    {
      "reference": "dashlit",
      "name": "DashLit",
      "website": "dashlit.cwec.dev/",
      "description": "Simple server startpage",
      "repo_url": "github.com/codewec/dashlit",
      "repo_key": "github.com/codewec/dashlit",
      "stars": null,
      "forks": 15,
      "updated_at": "34",
      "license": null,
      "tags": [
        "Dashboard"
      ],
      "readme_path": "knowledge/readmes/github.com__codewec__dashlit.md",
      "readme_status": "not_modified",
      "provenance": {
        "source": "selfhst/cdn directory/software.json",
        "fetched_at": "2026-03-29T05:09:50Z",
        "row_hash": "32a10660cddf76f35445a786257e80a5ce1b72cd4778abac753af22183af58f7"
      }
    },
    {
      "reference": "dashwise",
      "name": "Dashwise",
      "website": "dashwise-next.vercel.app/",
      "description": "All-in-one homelab dashboard",
      "repo_url": "github.com/andreasmolnardev/dashwise",
      "repo_key": "github.com/andreasmolnardev/dashwise",
      "stars": null,
      "forks": 11,
      "updated_at": "39",
      "license": null,
      "tags": [
        "Dashboard"
      ],
      "readme_path": "knowledge/readmes/github.com__andreasmolnardev__dashwise.md",
      "readme_status": "not_modified",
      "provenance": {
        "source": "selfhst/cdn directory/software.json",
        "fetched_at": "2026-03-29T05:09:50Z",
        "row_hash": "f3b1562763cfa76867021c37247d286dfe967edb4768535af785f4be8c62901a"
      }
    },
    {
      "reference": "dashy",
      "name": "Dashy",
      "website": "dashy.to",
      "description": "Dashboard with status-checking and widgets",
      "repo_url": "github.com/Lissy93/dashy",
      "repo_key": "github.com/Lissy93/dashy",
      "stars": null,
      "forks": 15,
      "updated_at": "40",
      "license": null,
      "tags": [
        "Dashboard"
      ],
      "readme_path": "knowledge/readmes/github.com__Lissy93__dashy.md",
      "readme_status": "not_modified",
      "provenance": {
        "source": "selfhst/cdn directory/software.json",
        "fetched_at": "2026-03-29T05:09:50Z",
        "row_hash": "efd44ed484b02824abc1893cf792175a34bffd41fddeff460a2734509798097a"
      }
    },
    {
      "reference": "databag",
      "name": "Databag",
      "website": "github.com/balzack/databag",
      "description": "Fast and lightweight messenger",
      "repo_url": "github.com/balzack/databag",
      "repo_key": "github.com/balzack/databag",
      "stars": null,
      "forks": 1,
      "updated_at": "39",
      "license": null,
      "tags": [
        "Messaging"
      ],
      "readme_path": "knowledge/readmes/github.com__balzack__databag.md",
      "readme_status": "not_modified",
      "provenance": {
        "source": "selfhst/cdn directory/software.json",
        "fetched_at": "2026-03-29T05:09:50Z",
        "row_hash": "7fca1c4137429943b00767fd116503c436aabe1b491cc542f447e6c1990a3273"
      }
    },
    {
      "reference": "databasus",
      "name": "Databasus",
      "website": "databasus.com",
      "description": "PostgreSQL backup tool",
      "repo_url": "github.com/databasus/databasus",
      "repo_key": "github.com/databasus/databasus",
      "stars": null,
      "forks": 1,
      "updated_at": "15",
      "license": null,
      "tags": [
        "Backups",
        "Database"
      ],
      "readme_path": "knowledge/readmes/github.com__databasus__databasus.md",
      "readme_status": "ok",
      "provenance": {
        "source": "selfhst/cdn directory/software.json",
        "fetched_at": "2026-03-29T05:09:50Z",
        "row_hash": "48f1c1218d7dd0951b3c454c5ec2ec7eafc9981f61b315d54a14c7dcb0fe898f"
      }
    },
    {
      "reference": "davical",
      "name": "DAViCal",
      "website": "www.davical.org/",
      "description": "Calendar storage and sharing",
      "repo_url": "gitlab.com/davical-project/davical",
      "repo_key": "gitlab.com/davical-project/davical",
      "stars": null,
      "forks": 13,
      "updated_at": "27",
      "license": null,
      "tags": [
        "Calendar"
      ],
      "readme_path": null,
      "readme_status": "error",
      "provenance": {
        "source": "selfhst/cdn directory/software.json",
        "fetched_at": "2026-03-29T05:09:50Z",
        "row_hash": "c2edced0eb71b6f62346074bc1241b4e0ca264b3548afde566813c675bc43c46"
      }
    },
    {
      "reference": "davis",
      "name": "Davis",
      "website": "github.com/users/tchapi/projects/1/views/1",
      "description": "Admin interface for sabre/dav",
      "repo_url": "github.com/tchapi/davis",
      "repo_key": "github.com/tchapi/davis",
      "stars": null,
      "forks": 15,
      "updated_at": "27",
      "license": null,
      "tags": [
        "CalDAV/CarDAV"
      ],
      "readme_path": "knowledge/readmes/github.com__tchapi__davis.md",
      "readme_status": "not_modified",
      "provenance": {
        "source": "selfhst/cdn directory/software.json",
        "fetched_at": "2026-03-29T05:09:50Z",
        "row_hash": "63a5e17684fe573dc16147eaf1497800ba3f4b88dee69899c2982acc44e5f8da"
      }
    },
    {
      "reference": "dawarich",
      "name": "Dawarich",
      "website": "dawarich.app",
      "description": "Self-hosted alternative to Google Location History",
      "repo_url": "github.com/Freika/dawarich",
      "repo_key": "github.com/Freika/dawarich",
      "stars": null,
      "forks": 0,
      "updated_at": "31",
      "license": null,
      "tags": [
        "GPS"
      ],
      "readme_path": "knowledge/readmes/github.com__Freika__dawarich.md",
      "readme_status": "not_modified",
      "provenance": {
        "source": "selfhst/cdn directory/software.json",
        "fetched_at": "2026-03-29T05:09:50Z",
        "row_hash": "3227367d6b6d1c4b4610836178d1a1851b9c9c9efba7433a706f39709c8a18e0"
      }
    },
    {
      "reference": "dbgate",
      "name": "DbGate",
      "website": "www.dbgate.io",
      "description": "Cross-platform database manager",
      "repo_url": "github.com/dbgate/dbgate",
      "repo_key": "github.com/dbgate/dbgate",
      "stars": null,
      "forks": 11,
      "updated_at": "34",
      "license": null,
      "tags": [
        "Database"
      ],
      "readme_path": "knowledge/readmes/github.com__dbgate__dbgate.md",
      "readme_status": "not_modified",
      "provenance": {
        "source": "selfhst/cdn directory/software.json",
        "fetched_at": "2026-03-29T05:09:50Z",
        "row_hash": "d683bc7f4ac3814f33e9947efe830a84528bb31ac8d073c8fbb70bb55d9811eb"
      }
    },
    {
      "reference": "ddclient",
      "name": "ddclient",
      "website": "ddclient.net",
      "description": "Dynamic DNS updates across a range of services",
      "repo_url": "github.com/ddclient/ddclient",
      "repo_key": "github.com/ddclient/ddclient",
      "stars": null,
      "forks": 10,
      "updated_at": "26",
      "license": null,
      "tags": [
        "DNS"
      ],
      "readme_path": "knowledge/readmes/github.com__ddclient__ddclient.md",
      "readme_status": "not_modified",
      "provenance": {
        "source": "selfhst/cdn directory/software.json",
        "fetched_at": "2026-03-29T05:09:50Z",
        "row_hash": "1e19491cec259668626469014951883c45a5d8b7dff405a72a84a5fe2f6f9f5c"
      }
    },
    {
      "reference": "ddns-updater",
      "name": "DDNS Updater",
      "website": "github.com/qdm12/ddns-updater",
      "description": "Periodic DNS record updates across DNS providers",
      "repo_url": "github.com/qdm12/ddns-updater",
      "repo_key": "github.com/qdm12/ddns-updater",
      "stars": null,
      "forks": 15,
      "updated_at": "15",
      "license": null,
      "tags": [
        "Automation",
        "DNS",
        "Networking",
        "Server Management"
      ],
      "readme_path": "knowledge/readmes/github.com__qdm12__ddns-updater.md",
      "readme_status": "not_modified",
      "provenance": {
        "source": "selfhst/cdn directory/software.json",
        "fetched_at": "2026-03-29T05:09:50Z",
        "row_hash": "fc470ee77e1cbb364b84a213a438c3bc23841a4805548546c9ada1a7fd158891"
      }
    },
    {
      "reference": "decypharr",
      "name": "Decypharr",
      "website": "github.com/sirrobot01/decypharr",
      "description": "qBittorrent implementation with Debrid support",
      "repo_url": "github.com/sirrobot01/decypharr",
      "repo_key": "github.com/sirrobot01/decypharr",
      "stars": null,
      "forks": 15,
      "updated_at": "15",
      "license": null,
      "tags": [
        "*arr",
        "Downloads"
      ],
      "readme_path": "knowledge/readmes/github.com__sirrobot01__decypharr.md",
      "readme_status": "not_modified",
      "provenance": {
        "source": "selfhst/cdn directory/software.json",
        "fetched_at": "2026-03-29T05:09:50Z",
        "row_hash": "e9b225d0e17b03031689c0b52bdf067ccbf78c8f80e7d69d1a3744a099967cc9"
      }
    },
    {
      "reference": "deepsubx",
      "name": "DeepSubX",
      "website": "github.com/garanda21/deepsubx",
      "description": "Use DeepL API to translate media subtitles",
      "repo_url": "github.com/garanda21/deepsubx",
      "repo_key": "github.com/garanda21/deepsubx",
      "stars": null,
      "forks": 15,
      "updated_at": "39",
      "license": null,
      "tags": [
        "Artificial Intelligence",
        "Subtitles"
      ],
      "readme_path": "knowledge/readmes/github.com__garanda21__deepsubx.md",
      "readme_status": "not_modified",
      "provenance": {
        "source": "selfhst/cdn directory/software.json",
        "fetched_at": "2026-03-29T05:09:50Z",
        "row_hash": "afcd129e7aec58171848f95e620910ed5b15e46fcc74b8cbeecdb33a04cfcb1f"
      }
    },
    {
      "reference": "defguard",
      "name": "Defguard",
      "website": "defguard.net",
      "description": "Enterprise VPN solution",
      "repo_url": "github.com/DefGuard/defguard",
      "repo_key": "github.com/DefGuard/defguard",
      "stars": null,
      "forks": 8,
      "updated_at": "32",
      "license": null,
      "tags": [
        "2FA",
        "Authentication",
        "Identity Management",
        "VPN"
      ],
      "readme_path": "knowledge/readmes/github.com__DefGuard__defguard.md",
      "readme_status": "not_modified",
      "provenance": {
        "source": "selfhst/cdn directory/software.json",
        "fetched_at": "2026-03-29T05:09:50Z",
        "row_hash": "9b8d6836e8872fb96d76341ce7b2ad0548192718746022bff4fe358664350f31"
      }
    },
    {
      "reference": "deployrr",
      "name": "Deployrr",
      "website": "www.deployrr.app",
      "description": "Automated homelab setups using Docker",
      "repo_url": "github.com/SimpleHomelab/Deployrr",
      "repo_key": "github.com/SimpleHomelab/Deployrr",
      "stars": null,
      "forks": 8,
      "updated_at": "27",
      "license": null,
      "tags": [
        "Deployment",
        "Docker"
      ],
      "readme_path": "knowledge/readmes/github.com__SimpleHomelab__Deployrr.md",
      "readme_status": "not_modified",
      "provenance": {
        "source": "selfhst/cdn directory/software.json",
        "fetched_at": "2026-03-29T05:09:50Z",
        "row_hash": "cc0a38ab244354e75042b83e136cd2fd6c5214187b490a4135107a612170842b"
      }
    },
    {
      "reference": "dim",
      "name": "Dim",
      "website": "github.com/Dusk-Labs/dim",
      "description": "Media manager and organizer with a minimal setup",
      "repo_url": "github.com/Dusk-Labs/dim",
      "repo_key": "github.com/Dusk-Labs/dim",
      "stars": null,
      "forks": 0,
      "updated_at": "32",
      "license": null,
      "tags": [
        "Media Streaming"
      ],
      "readme_path": "knowledge/readmes/github.com__Dusk-Labs__dim.md",
      "readme_status": "not_modified",
      "provenance": {
        "source": "selfhst/cdn directory/software.json",
        "fetched_at": "2026-03-29T05:09:50Z",
        "row_hash": "dcb511bee90b979c424c489dcddc42c0be3ce7e39937cc561858dea5845da2d6"
      }
    },
    {
      "reference": "directus",
      "name": "Directus",
      "website": "directus.io",
      "description": "Headless CMS and backend for custom builds",
      "repo_url": "github.com/directus/directus",
      "repo_key": "github.com/directus/directus",
      "stars": null,
      "forks": 8,
      "updated_at": "39",
      "license": null,
      "tags": [
        "Content Management",
        "Database"
      ],
      "readme_path": "knowledge/readmes/github.com__directus__directus.md",
      "readme_status": "not_modified",
      "provenance": {
        "source": "selfhst/cdn directory/software.json",
        "fetched_at": "2026-03-29T05:09:50Z",
        "row_hash": "d832aa5122f33b1cb7a5d93e5af7a8eccf58598ab19bd965df3c708508b58559"
      }
    },
    {
      "reference": "discourse",
      "name": "Discourse",
      "website": "www.discourse.org",
      "description": "Online home for communities",
      "repo_url": "github.com/discourse/discourse",
      "repo_key": "github.com/discourse/discourse",
      "stars": null,
      "forks": 10,
      "updated_at": "31",
      "license": null,
      "tags": [
        "Forums"
      ],
      "readme_path": "knowledge/readmes/github.com__discourse__discourse.md",
      "readme_status": "not_modified",
      "provenance": {
        "source": "selfhst/cdn directory/software.json",
        "fetched_at": "2026-03-29T05:09:50Z",
        "row_hash": "3fadd1bcd1110cf9d13befd27c427cc81c3449a5629a5a2a43964dd209e8d436"
      }
    },
    {
      "reference": "diskover",
      "name": "Diskover",
      "website": "diskoverdata.com",
      "description": "File indexer, search engine, and data management platform",
      "repo_url": "github.com/diskoverdata/diskover-community",
      "repo_key": "github.com/diskoverdata/diskover-community",
      "stars": null,
      "forks": 1,
      "updated_at": "27",
      "license": null,
      "tags": [
        "File Management",
        "Search"
      ],
      "readme_path": "knowledge/readmes/github.com__diskoverdata__diskover-community.md",
      "readme_status": "not_modified",
      "provenance": {
        "source": "selfhst/cdn directory/software.json",
        "fetched_at": "2026-03-29T05:09:50Z",
        "row_hash": "902d85ccd51da40b59623ddeccdad04ad84808b6238c93fc5d39de7b7602ff4d"
      }
    },
    {
      "reference": "dispatcharr",
      "name": "Dispatcharr",
      "website": "github.com/Dispatcharr/Dispatcharr",
      "description": "IPTV stream and EPG data management",
      "repo_url": "github.com/Dispatcharr/Dispatcharr",
      "repo_key": "github.com/Dispatcharr/Dispatcharr",
      "stars": null,
      "forks": 0,
      "updated_at": "21",
      "license": null,
      "tags": [
        "*arr",
        "Media Streaming"
      ],
      "readme_path": "knowledge/readmes/github.com__Dispatcharr__Dispatcharr.md",
      "readme_status": "not_modified",
      "provenance": {
        "source": "selfhst/cdn directory/software.json",
        "fetched_at": "2026-03-29T05:09:50Z",
        "row_hash": "b6ceb9086bfab4bb22c5a5cf0b0325e538a47afc6bc8e2719dbfb2bb5cea395c"
      }
    },
    {
      "reference": "dittofeed",
      "name": "Dittofeed",
      "website": "dittofeed.com/",
      "description": "Omni-channel customer engagement platform",
      "repo_url": "github.com/dittofeed/dittofeed",
      "repo_key": "github.com/dittofeed/dittofeed",
      "stars": null,
      "forks": 15,
      "updated_at": "39",
      "license": null,
      "tags": [
        "Marketing"
      ],
      "readme_path": "knowledge/readmes/github.com__dittofeed__dittofeed.md",
      "readme_status": "not_modified",
      "provenance": {
        "source": "selfhst/cdn directory/software.json",
        "fetched_at": "2026-03-29T05:09:50Z",
        "row_hash": "0fa990dc72453f83d0d1fd347d01286285cef893fc237e6725402ec95e040b95"
      }
    },
    {
      "reference": "diun",
      "name": "Diun",
      "website": "crazymax.dev/diun/",
      "description": "Docker image update notifications",
      "repo_url": "github.com/crazy-max/diun",
      "repo_key": "github.com/crazy-max/diun",
      "stars": null,
      "forks": 15,
      "updated_at": "15",
      "license": null,
      "tags": [
        "Docker",
        "Updates"
      ],
      "readme_path": "knowledge/readmes/github.com__crazy-max__diun.md",
      "readme_status": "not_modified",
      "provenance": {
        "source": "selfhst/cdn directory/software.json",
        "fetched_at": "2026-03-29T05:09:50Z",
        "row_hash": "7e950aab0fc8c9a93d2956e808be0c513456ebf46340c84835fb282f531f7304"
      }
    },
    {
      "reference": "diyhue",
      "name": "diyHue",
      "website": "diyhue.org/",
      "description": "Open source Hue Bridge emulator",
      "repo_url": "github.com/diyhue/diyHue",
      "repo_key": "github.com/diyhue/diyHue",
      "stars": null,
      "forks": 8,
      "updated_at": "30",
      "license": null,
      "tags": [
        "Home Automation",
        "Smart Home"
      ],
      "readme_path": "knowledge/readmes/github.com__diyhue__diyHue.md",
      "readme_status": "not_modified",
      "provenance": {
        "source": "selfhst/cdn directory/software.json",
        "fetched_at": "2026-03-29T05:09:50Z",
        "row_hash": "ef95be85c7e2d1b2d24a25fd2ee894fe8e1759cfb29e13704340cb94749782f6"
      }
    },
    {
      "reference": "docassemble",
      "name": "Docassemble",
      "website": "docassemble.org",
      "description": "System for guided interviews and document assembly",
      "repo_url": "github.com/jhpyle/docassemble",
      "repo_key": "github.com/jhpyle/docassemble",
      "stars": null,
      "forks": 15,
      "updated_at": "21",
      "license": null,
      "tags": [
        "Surveys and Forms"
      ],
      "readme_path": "knowledge/readmes/github.com__jhpyle__docassemble.md",
      "readme_status": "not_modified",
      "provenance": {
        "source": "selfhst/cdn directory/software.json",
        "fetched_at": "2026-03-29T05:09:50Z",
        "row_hash": "76d478688c4dd2dba8effa02874b45bad327e561b1c80fd5b5a6858eee6df8eb"
      }
    },
    {
      "reference": "dockcheck",
      "name": "Dockcheck",
      "website": "github.com/mag37/dockcheck",
      "description": "CLI tool for Docker container updates and notifications",
      "repo_url": "github.com/mag37/dockcheck",
      "repo_key": "github.com/mag37/dockcheck",
      "stars": null,
      "forks": 11,
      "updated_at": "33",
      "license": null,
      "tags": [
        "Docker",
        "Updates"
      ],
      "readme_path": "knowledge/readmes/github.com__mag37__dockcheck.md",
      "readme_status": "not_modified",
      "provenance": {
        "source": "selfhst/cdn directory/software.json",
        "fetched_at": "2026-03-29T05:09:50Z",
        "row_hash": "b2b7bf38f3d86affa7ee524958d7aa39ed78d142ff486339266dfc3cf74f9d40"
      }
    },
    {
      "reference": "docker-registry-browser",
      "name": "Docker Registry Browser",
      "website": "github.com/klausmeyer/docker-registry-browser",
      "description": "Web interface for the Docker Registry HTTP API",
      "repo_url": "github.com/klausmeyer/docker-registry-browser",
      "repo_key": "github.com/klausmeyer/docker-registry-browser",
      "stars": null,
      "forks": 15,
      "updated_at": "31",
      "license": null,
      "tags": [
        "Container Registry",
        "Docker"
      ],
      "readme_path": "knowledge/readmes/github.com__klausmeyer__docker-registry-browser.md",
      "readme_status": "not_modified",
      "provenance": {
        "source": "selfhst/cdn directory/software.json",
        "fetched_at": "2026-03-29T05:09:50Z",
        "row_hash": "7e9462c9afff5bf102d1d50cbd00da268397babdbaf5eb5a001677332ff6a874"
      }
    },
    {
      "reference": "docker-socket-proxy",
      "name": "Docker Socket Proxy",
      "website": "github.com/Tecnativa/docker-socket-proxy",
      "description": "Socket proxy for the Docker API",
      "repo_url": "github.com/Tecnativa/docker-socket-proxy",
      "repo_key": "github.com/Tecnativa/docker-socket-proxy",
      "stars": null,
      "forks": 1,
      "updated_at": "30",
      "license": null,
      "tags": [
        "Docker",
        "Reverse Proxy",
        "Server Management"
      ],
      "readme_path": "knowledge/readmes/github.com__Tecnativa__docker-socket-proxy.md",
      "readme_status": "not_modified",
      "provenance": {
        "source": "selfhst/cdn directory/software.json",
        "fetched_at": "2026-03-29T05:09:50Z",
        "row_hash": "04a61f9d97a2952802322593f392ab84bc8721325e50889e0e57dfa9e3d6a827"
      }
    },
    {
      "reference": "docker-volume-backup",
      "name": "Docker Volume Backup",
      "website": "offen.github.io/docker-volume-backup/",
      "description": "Backup Docker volumes to compatible storage backends",
      "repo_url": "github.com/offen/docker-volume-backup",
      "repo_key": "github.com/offen/docker-volume-backup",
      "stars": null,
      "forks": 16,
      "updated_at": "15",
      "license": null,
      "tags": [
        "Backups",
        "Docker"
      ],
      "readme_path": "knowledge/readmes/github.com__offen__docker-volume-backup.md",
      "readme_status": "not_modified",
      "provenance": {
        "source": "selfhst/cdn directory/software.json",
        "fetched_at": "2026-03-29T05:09:50Z",
        "row_hash": "a6bdc93b4b2922119e4feb44350ac164927cd414fde900e01a8345f79fa65fa3"
      }
    },
    {
      "reference": "docker-php-startpage",
      "name": "docker-php-startpage",
      "website": "github.com/loganmarchione/docker-php-startpage",
      "description": "PHP-based startpage and status monitor in Docker",
      "repo_url": "github.com/loganmarchione/docker-php-startpage",
      "repo_key": "github.com/loganmarchione/docker-php-startpage",
      "stars": null,
      "forks": 15,
      "updated_at": "38",
      "license": null,
      "tags": [
        "Dashboard",
        "Docker"
      ],
      "readme_path": "knowledge/readmes/github.com__loganmarchione__docker-php-startpage.md",
      "readme_status": "not_modified",
      "provenance": {
        "source": "selfhst/cdn directory/software.json",
        "fetched_at": "2026-03-29T05:09:50Z",
        "row_hash": "9a5e0ca1820798abcecb02668895b9cbd137a71d806bdd469f05282ac5361faf"
      }
    },
    {
      "reference": "docker-staticmaps",
      "name": "docker-staticmaps",
      "website": "dietrichmax.github.io/docker-staticmaps/",
      "description": "API for rendering static map images",
      "repo_url": "github.com/dietrichmax/docker-staticmaps",
      "repo_key": "github.com/dietrichmax/docker-staticmaps",
      "stars": null,
      "forks": 8,
      "updated_at": "39",
      "license": null,
      "tags": [
        "Development",
        "Maps"
      ],
      "readme_path": "knowledge/readmes/github.com__dietrichmax__docker-staticmaps.md",
      "readme_status": "not_modified",
      "provenance": {
        "source": "selfhst/cdn directory/software.json",
        "fetched_at": "2026-03-29T05:09:50Z",
        "row_hash": "421a138b4d8c5da053100624c351e8df98ba8de3bae40b034fbab69c6c5ac3cf"
      }
    },
    {
      "reference": "dockerizalo",
      "name": "Dockerizalo",
      "website": "github.com/undernightcore/dockerizalo",
      "description": "Simple container deployment and management platform",
      "repo_url": "github.com/undernightcore/dockerizalo",
      "repo_key": "github.com/undernightcore/dockerizalo",
      "stars": null,
      "forks": 0,
      "updated_at": "39",
      "license": null,
      "tags": [
        "Deployment"
      ],
      "readme_path": "knowledge/readmes/github.com__undernightcore__dockerizalo.md",
      "readme_status": "not_modified",
      "provenance": {
        "source": "selfhst/cdn directory/software.json",
        "fetched_at": "2026-03-29T05:09:50Z",
        "row_hash": "790d78bbfb599d25d4a13be6662bc1ab82fb13458745c6c3774b94e503633348"
      }
    },
    {
      "reference": "dockflare",
      "name": "DockFlare",
      "website": "dockflare.app",
      "description": "Cloudflare Tunnel controller",
      "repo_url": "github.com/ChrispyBacon-dev/DockFlare",
      "repo_key": "github.com/ChrispyBacon-dev/DockFlare",
      "stars": null,
      "forks": 8,
      "updated_at": "30",
      "license": null,
      "tags": [
        "Remote Access",
        "Reverse Proxy"
      ],
      "readme_path": "knowledge/readmes/github.com__ChrispyBacon-dev__DockFlare.md",
      "readme_status": "not_modified",
      "provenance": {
        "source": "selfhst/cdn directory/software.json",
        "fetched_at": "2026-03-29T05:09:50Z",
        "row_hash": "2e500a19579ba4a5141fc25de1f29565b233107f6eb241b8d3b1a9cf4a1928f5"
      }
    },
    {
      "reference": "dockge",
      "name": "Dockge",
      "website": "dockge.kuma.pet",
      "description": "Easy-to-use docker compose stack manager",
      "repo_url": "github.com/louislam/dockge",
      "repo_key": "github.com/louislam/dockge",
      "stars": null,
      "forks": 15,
      "updated_at": "39",
      "license": null,
      "tags": [
        "Deployment",
        "Docker",
        "Server Management"
      ],
      "readme_path": "knowledge/readmes/github.com__louislam__dockge.md",
      "readme_status": "not_modified",
      "provenance": {
        "source": "selfhst/cdn directory/software.json",
        "fetched_at": "2026-03-29T05:09:50Z",
        "row_hash": "949d1d63e2be59033d6461fb657fb6a20c00d8991fd0d5ae0905febbd180a2ce"
      }
    },
    {
      "reference": "dockhand",
      "name": "Dockhand",
      "website": "dockhand.pro",
      "description": "Docker management and orchestration app",
      "repo_url": "github.com/Finsys/dockhand",
      "repo_key": "github.com/Finsys/dockhand",
      "stars": null,
      "forks": 8,
      "updated_at": "34",
      "license": null,
      "tags": [
        "Deployment",
        "Docker"
      ],
      "readme_path": "knowledge/readmes/github.com__Finsys__dockhand.md",
      "readme_status": "not_modified",
      "provenance": {
        "source": "selfhst/cdn directory/software.json",
        "fetched_at": "2026-03-29T05:09:50Z",
        "row_hash": "22d247a2d625597988f6ce39b9213e7a570713bd1f3afa1bf6fddfa30d5f6321"
      }
    },
    {
      "reference": "docking-station",
      "name": "Docking Station",
      "website": "github.com/LooLzzz/docking-station",
      "description": "Web app for managing and updating Docker containers",
      "repo_url": "github.com/LooLzzz/docking-station",
      "repo_key": "github.com/LooLzzz/docking-station",
      "stars": null,
      "forks": 8,
      "updated_at": "30",
      "license": null,
      "tags": [
        "Docker",
        "Updates"
      ],
      "readme_path": "knowledge/readmes/github.com__LooLzzz__docking-station.md",
      "readme_status": "not_modified",
      "provenance": {
        "source": "selfhst/cdn directory/software.json",
        "fetched_at": "2026-03-29T05:09:50Z",
        "row_hash": "b13915eef636146ad644722503007e84ebdfc607ebb4b029bc1439d9cc53cdae"
      }
    },
    {
      "reference": "dockman",
      "name": "Dockman",
      "website": "dockman.radn.dev/",
      "description": "Docker Compose file simplification",
      "repo_url": "github.com/RA341/dockman",
      "repo_key": "github.com/RA341/dockman",
      "stars": null,
      "forks": 0,
      "updated_at": "39",
      "license": null,
      "tags": [
        "Deployment",
        "Docker"
      ],
      "readme_path": "knowledge/readmes/github.com__RA341__dockman.md",
      "readme_status": "not_modified",
      "provenance": {
        "source": "selfhst/cdn directory/software.json",
        "fetched_at": "2026-03-29T05:09:50Z",
        "row_hash": "eef1357b039ac92e83790e89487fc5c032501dab5513d002645addd40c7b2f4e"
      }
    },
    {
      "reference": "dockpeek",
      "name": "Dockpeek",
      "website": "github.com/dockpeek/dockpeek",
      "description": "Dashboard for exposed Docker container ports",
      "repo_url": "github.com/dockpeek/dockpeek",
      "repo_key": "github.com/dockpeek/dockpeek",
      "stars": null,
      "forks": 15,
      "updated_at": "21",
      "license": null,
      "tags": [
        "Dashboard",
        "Docker",
        "Server Management"
      ],
      "readme_path": "knowledge/readmes/github.com__dockpeek__dockpeek.md",
      "readme_status": "not_modified",
      "provenance": {
        "source": "selfhst/cdn directory/software.json",
        "fetched_at": "2026-03-29T05:09:50Z",
        "row_hash": "3c3a6e74d680a871bfa416f5cab4294888b221be147efc0a8e5b2228613feddc"
      }
    },
    {
      "reference": "dockstarter",
      "name": "DockSTARTer",
      "website": "dockstarter.com/",
      "description": "Quick and easy Docker deployment platform",
      "repo_url": "github.com/GhostWriters/DockSTARTer",
      "repo_key": "github.com/GhostWriters/DockSTARTer",
      "stars": null,
      "forks": 15,
      "updated_at": "33",
      "license": null,
      "tags": [
        "Deployment",
        "Server Management"
      ],
      "readme_path": "knowledge/readmes/github.com__GhostWriters__DockSTARTer.md",
      "readme_status": "not_modified",
      "provenance": {
        "source": "selfhst/cdn directory/software.json",
        "fetched_at": "2026-03-29T05:09:50Z",
        "row_hash": "a25712d112c1a18e085a70df76579e5ce2897b848a92a5e5069cb510c7cc0d9b"
      }
    },
    {
      "reference": "dockwatch",
      "name": "Dockwatch",
      "website": "dockwatch.wiki",
      "description": "Simple UI for managing container updates and notifications",
      "repo_url": "github.com/Notifiarr/dockwatch",
      "repo_key": "github.com/Notifiarr/dockwatch",
      "stars": null,
      "forks": 15,
      "updated_at": "27",
      "license": null,
      "tags": [
        "Docker",
        "Server Management"
      ],
      "readme_path": "knowledge/readmes/github.com__Notifiarr__dockwatch.md",
      "readme_status": "not_modified",
      "provenance": {
        "source": "selfhst/cdn directory/software.json",
        "fetched_at": "2026-03-29T05:09:50Z",
        "row_hash": "add2ee307867fcc988945a95e6e391b17fc0425e2b13094f7eca0ba869ce1881"
      }
    },
    {
      "reference": "docmost",
      "name": "Docmost",
      "website": "docmost.com",
      "description": "Collaborative documentation and wiki software",
      "repo_url": "github.com/docmost/docmost",
      "repo_key": "github.com/docmost/docmost",
      "stars": null,
      "forks": 0,
      "updated_at": "39",
      "license": null,
      "tags": [
        "Wiki",
        "Workspace"
      ],
      "readme_path": "knowledge/readmes/github.com__docmost__docmost.md",
      "readme_status": "not_modified",
      "provenance": {
        "source": "selfhst/cdn directory/software.json",
        "fetched_at": "2026-03-29T05:09:50Z",
        "row_hash": "8a4ace2479778658ffd85157005b60c411dd62baac2308da9eb179fac1388d7e"
      }
    },
    {
      "reference": "doco-cd",
      "name": "Doco-CD",
      "website": "github.com/kimdre/doco-cd",
      "description": "Docker Compose continuous deployment",
      "repo_url": "github.com/kimdre/doco-cd",
      "repo_key": "github.com/kimdre/doco-cd",
      "stars": null,
      "forks": 1,
      "updated_at": "15",
      "license": null,
      "tags": [
        "Deployment",
        "Docker"
      ],
      "readme_path": "knowledge/readmes/github.com__kimdre__doco-cd.md",
      "readme_status": "not_modified",
      "provenance": {
        "source": "selfhst/cdn directory/software.json",
        "fetched_at": "2026-03-29T05:09:50Z",
        "row_hash": "10348fd98841bb848692732fa86ac73f4bdb2f401588afe540471cb8fcb0a622"
      }
    },
    {
      "reference": "docs-collaboration",
      "name": "Docs",
      "website": "docs.la-suite.eu/",
      "description": "Collaborative note-taking, wiki, and documentation",
      "repo_url": "github.com/suitenumerique/docs",
      "repo_key": "github.com/suitenumerique/docs",
      "stars": null,
      "forks": 15,
      "updated_at": "30",
      "license": null,
      "tags": [
        "Note-Taking",
        "Wiki"
      ],
      "readme_path": "knowledge/readmes/github.com__suitenumerique__docs.md",
      "readme_status": "not_modified",
      "provenance": {
        "source": "selfhst/cdn directory/software.json",
        "fetched_at": "2026-03-29T05:09:50Z",
        "row_hash": "474ff62afd7dc50ad4303017c330825ccef0fd1d5a48b9fd0a2b24b949d6b4f6"
      }
    },
    {
      "reference": "docspell",
      "name": "Docspell",
      "website": "docspell.org",
      "description": "Organize documents from various sources",
      "repo_url": "github.com/eikek/docspell",
      "repo_key": "github.com/eikek/docspell",
      "stars": null,
      "forks": 0,
      "updated_at": "12",
      "license": null,
      "tags": [
        "Document Management"
      ],
      "readme_path": "knowledge/readmes/github.com__eikek__docspell.md",
      "readme_status": "not_modified",
      "provenance": {
        "source": "selfhst/cdn directory/software.json",
        "fetched_at": "2026-03-29T05:09:50Z",
        "row_hash": "f02e25d368e8c66c9b75cbad9001ad4f39b4b664d1bbda82531d9693176cca9c"
      }
    },
    {
      "reference": "documenso",
      "name": "Documenso",
      "website": "documenso.com",
      "description": "Open source document signing",
      "repo_url": "github.com/documenso/documenso",
      "repo_key": "github.com/documenso/documenso",
      "stars": null,
      "forks": 0,
      "updated_at": "39",
      "license": null,
      "tags": [
        "Document Signing"
      ],
      "readme_path": "knowledge/readmes/github.com__documenso__documenso.md",
      "readme_status": "not_modified",
      "provenance": {
        "source": "selfhst/cdn directory/software.json",
        "fetched_at": "2026-03-29T05:09:50Z",
        "row_hash": "728aee89d7e80c11a01ee72fa59a462f1208a536cd8702c9f1eee3edd94bb5c4"
      }
    },
    {
      "reference": "docusaurus",
      "name": "Docusaurus",
      "website": "docusaurus.io",
      "description": "Easy to maintain open source docs",
      "repo_url": "github.com/facebook/docusaurus",
      "repo_key": "github.com/facebook/docusaurus",
      "stars": null,
      "forks": 15,
      "updated_at": "39",
      "license": null,
      "tags": [
        "Wiki"
      ],
      "readme_path": "knowledge/readmes/github.com__facebook__docusaurus.md",
      "readme_status": "not_modified",
      "provenance": {
        "source": "selfhst/cdn directory/software.json",
        "fetched_at": "2026-03-29T05:09:50Z",
        "row_hash": "31cdb146f566670e36f633e2cd9bc060ffbd7c4b11c0c2d5c97b3a99557ba031"
      }
    },
    {
      "reference": "docuseal",
      "name": "DocuSeal",
      "website": "www.docuseal.com",
      "description": "Create, fill, and sign digital documents",
      "repo_url": "github.com/docusealco/docuseal",
      "repo_key": "github.com/docusealco/docuseal",
      "stars": null,
      "forks": 0,
      "updated_at": "31",
      "license": null,
      "tags": [
        "Document Signing"
      ],
      "readme_path": "knowledge/readmes/github.com__docusealco__docuseal.md",
      "readme_status": "not_modified",
      "provenance": {
        "source": "selfhst/cdn directory/software.json",
        "fetched_at": "2026-03-29T05:09:50Z",
        "row_hash": "a80becad697133e05d464394e757150878a5a2a8a234e4037977f5023394654b"
      }
    },
    {
      "reference": "dokku",
      "name": "Dokku",
      "website": "dokku.com",
      "description": "Open source platform-as-a-service",
      "repo_url": "github.com/dokku/dokku",
      "repo_key": "github.com/dokku/dokku",
      "stars": null,
      "forks": 15,
      "updated_at": "33",
      "license": null,
      "tags": [
        "Deployment"
      ],
      "readme_path": "knowledge/readmes/github.com__dokku__dokku.md",
      "readme_status": "not_modified",
      "provenance": {
        "source": "selfhst/cdn directory/software.json",
        "fetched_at": "2026-03-29T05:09:50Z",
        "row_hash": "6b07e940ce2299be84c3f03acad1fc9080378c036bbda2247da55210a9f8c841"
      }
    },
    {
      "reference": "dokploy",
      "name": "Dokploy",
      "website": "dokploy.com/",
      "description": "Application deployment and management platform",
      "repo_url": "github.com/Dokploy/dokploy",
      "repo_key": "github.com/Dokploy/dokploy",
      "stars": null,
      "forks": 8,
      "updated_at": "39",
      "license": null,
      "tags": [
        "Deployment",
        "Platform"
      ],
      "readme_path": "knowledge/readmes/github.com__Dokploy__dokploy.md",
      "readme_status": "ok",
      "provenance": {
        "source": "selfhst/cdn directory/software.json",
        "fetched_at": "2026-03-29T05:09:50Z",
        "row_hash": "c144c3d633e81fb7c8c1de86f9c642a9d79928c82e7a9edd344d288957ba1764"
      }
    },
    {
      "reference": "dokuwiki",
      "name": "DokuWiki",
      "website": "http://www.dokuwiki.org",
      "description": "Open source wiki engine",
      "repo_url": "github.com/dokuwiki/dokuwiki",
      "repo_key": "github.com/dokuwiki/dokuwiki",
      "stars": null,
      "forks": 10,
      "updated_at": "27",
      "license": null,
      "tags": [
        "Wiki"
      ],
      "readme_path": "knowledge/readmes/github.com__dokuwiki__dokuwiki.md",
      "readme_status": "not_modified",
      "provenance": {
        "source": "selfhst/cdn directory/software.json",
        "fetched_at": "2026-03-29T05:09:50Z",
        "row_hash": "2496a3ae2c99edd3109cf79d9459a20a20112f07330c2de99c4fa451fb14e806"
      }
    },
    {
      "reference": "dolibarr",
      "name": "Dolibarr",
      "website": "www.dolibarr.org",
      "description": "Open source ERP and CRM for business",
      "repo_url": "github.com/Dolibarr/dolibarr",
      "repo_key": "github.com/Dolibarr/dolibarr",
      "stars": null,
      "forks": 11,
      "updated_at": "27",
      "license": null,
      "tags": [
        "ERP"
      ],
      "readme_path": "knowledge/readmes/github.com__Dolibarr__dolibarr.md",
      "readme_status": "ok",
      "provenance": {
        "source": "selfhst/cdn directory/software.json",
        "fetched_at": "2026-03-29T05:09:50Z",
        "row_hash": "167c922428d9eb8708cc65f3063bff7a3c411ed925e288f7620c6e7104207ab4"
      }
    }
  ]
}