{
  "chunk": 15,
  "count": 50,
  "generated_at": "2026-03-04T17:47:43Z",
  "items": [
    {
      "reference": "nixopus",
      "name": "Nixopus",
      "website": "nixopus.com",
      "description": "Deploy, manage, and scale infrastructure",
      "repo_url": "github.com/raghavyuva/nixopus",
      "repo_key": "github.com/raghavyuva/nixopus",
      "stars": null,
      "forks": 8,
      "updated_at": "15",
      "license": null,
      "tags": [
        "Deployment",
        "Server Management"
      ],
      "readme_path": "knowledge/readmes/github.com__raghavyuva__nixopus.md",
      "readme_status": "not_modified",
      "provenance": {
        "source": "selfhst/cdn directory/software.json",
        "fetched_at": "2026-03-04T17:40:41Z",
        "row_hash": "857bb5f272dbc05da16699772e2ad5aaa660595e63edd3ea7d187c19dc461034"
      }
    },
    {
      "reference": "nocobase",
      "name": "NocoBase",
      "website": "www.nocobase.com",
      "description": "No-code platform for building business applications",
      "repo_url": "github.com/nocobase/nocobase",
      "repo_key": "github.com/nocobase/nocobase",
      "stars": null,
      "forks": 8,
      "updated_at": "41",
      "license": null,
      "tags": [
        "No-Code / Low-Code"
      ],
      "readme_path": "knowledge/readmes/github.com__nocobase__nocobase.md",
      "readme_status": "not_modified",
      "provenance": {
        "source": "selfhst/cdn directory/software.json",
        "fetched_at": "2026-03-04T17:40:41Z",
        "row_hash": "3571037ab320d5bb03145995b79c89c8d9b2931387814177c4d3409637ee1725"
      }
    },
    {
      "reference": "nocodb",
      "name": "NocoDB",
      "website": "nocodb.com",
      "description": "Turn any SQL-based database into a smart spreadsheet",
      "repo_url": "github.com/nocodb/nocodb",
      "repo_key": "github.com/nocodb/nocodb",
      "stars": null,
      "forks": 8,
      "updated_at": "41",
      "license": null,
      "tags": [
        "Database",
        "No-Code / Low-Code",
        "Relational Database",
        "Spreadsheet"
      ],
      "readme_path": "knowledge/readmes/github.com__nocodb__nocodb.md",
      "readme_status": "not_modified",
      "provenance": {
        "source": "selfhst/cdn directory/software.json",
        "fetched_at": "2026-03-04T17:40:41Z",
        "row_hash": "0c587982e14910fb40867902b18cefba68b590b1d5015de25a9412098fe7a97f"
      }
    },
    {
      "reference": "node-red",
      "name": "Node-RED",
      "website": "http://nodered.org",
      "description": "Low-code programming for event-driven applications",
      "repo_url": "github.com/node-red/node-red",
      "repo_key": "github.com/node-red/node-red",
      "stars": null,
      "forks": 1,
      "updated_at": "21",
      "license": null,
      "tags": [
        "Workflow Automation"
      ],
      "readme_path": "knowledge/readmes/github.com__node-red__node-red.md",
      "readme_status": "not_modified",
      "provenance": {
        "source": "selfhst/cdn directory/software.json",
        "fetched_at": "2026-03-04T17:40:41Z",
        "row_hash": "3e3ad0ad294d7f369ff0133f78ca6f28acd5299f31b9b5ea649bccdc7e495fd4"
      }
    },
    {
      "reference": "nodebb",
      "name": "NodeBB",
      "website": "nodebb.org",
      "description": "Forum software built for the modern web",
      "repo_url": "github.com/NodeBB/NodeBB",
      "repo_key": "github.com/NodeBB/NodeBB",
      "stars": null,
      "forks": 11,
      "updated_at": "21",
      "license": null,
      "tags": [
        "ActivityPub / Fediverse",
        "Forums"
      ],
      "readme_path": "knowledge/readmes/github.com__NodeBB__NodeBB.md",
      "readme_status": "not_modified",
      "provenance": {
        "source": "selfhst/cdn directory/software.json",
        "fetched_at": "2026-03-04T17:40:41Z",
        "row_hash": "aac5ad5510c062ab65100e8fd9a7d26c9fc1c55d9901c9070388d2cf80165810"
      }
    },
    {
      "reference": "nodecast-tv",
      "name": "nodecast-tv",
      "website": "github.com/technomancer702/nodecast-tv",
      "description": "Web-based IPTV player",
      "repo_url": "github.com/technomancer702/nodecast-tv",
      "repo_key": "github.com/technomancer702/nodecast-tv",
      "stars": null,
      "forks": 11,
      "updated_at": "21",
      "license": null,
      "tags": [
        "Media Streaming",
        "Television"
      ],
      "readme_path": "knowledge/readmes/github.com__technomancer702__nodecast-tv.md",
      "readme_status": "not_modified",
      "provenance": {
        "source": "selfhst/cdn directory/software.json",
        "fetched_at": "2026-03-04T17:40:41Z",
        "row_hash": "b38f532f53cc895a979f955b03166aafb0b228ee03eb98c6a4c8fc4b345eb3e1"
      }
    },
    {
      "reference": "novus-mail",
      "name": "Nortix Mail",
      "website": "github.com/Zhoros/NortixMail",
      "description": "Disposable e-mail server with an easy configuration",
      "repo_url": "github.com/Zhoros/NortixMail",
      "repo_key": "github.com/Zhoros/NortixMail",
      "stars": null,
      "forks": 8,
      "updated_at": "21",
      "license": null,
      "tags": [
        "Email"
      ],
      "readme_path": "knowledge/readmes/github.com__Zhoros__NortixMail.md",
      "readme_status": "not_modified",
      "provenance": {
        "source": "selfhst/cdn directory/software.json",
        "fetched_at": "2026-03-04T17:40:41Z",
        "row_hash": "f65f9bb53779692df8e2c8754645bb9902ca45db65cfdffcbd8ada8c91ca5fab"
      }
    },
    {
      "reference": "note-mark",
      "name": "Note Mark",
      "website": "notemark.docs.enchantedcode.co.uk/",
      "description": "Lightning fast and minimal web-based Markdown notes app",
      "repo_url": "github.com/enchant97/note-mark",
      "repo_key": "github.com/enchant97/note-mark",
      "stars": null,
      "forks": 0,
      "updated_at": "41",
      "license": null,
      "tags": [
        "Note-Taking"
      ],
      "readme_path": "knowledge/readmes/github.com__enchant97__note-mark.md",
      "readme_status": "not_modified",
      "provenance": {
        "source": "selfhst/cdn directory/software.json",
        "fetched_at": "2026-03-04T17:40:41Z",
        "row_hash": "94d5a29c23e052f41e9748716ec16c58c34db5efd8cb973565fb7187bd9622c7"
      }
    },
    {
      "reference": "notediscovery",
      "name": "NoteDiscovery",
      "website": "www.notediscovery.com",
      "description": "Lightweight Obsidian-like note-taking app",
      "repo_url": "github.com/gamosoft/NoteDiscovery",
      "repo_key": "github.com/gamosoft/NoteDiscovery",
      "stars": null,
      "forks": 15,
      "updated_at": "21",
      "license": null,
      "tags": [
        "Note-Taking",
        "Wiki"
      ],
      "readme_path": "knowledge/readmes/github.com__gamosoft__NoteDiscovery.md",
      "readme_status": "not_modified",
      "provenance": {
        "source": "selfhst/cdn directory/software.json",
        "fetched_at": "2026-03-04T17:40:41Z",
        "row_hash": "4b97b8d13835128a9bfce8fe24f20f7971795251de0ee84595da64b137b00187"
      }
    },
    {
      "reference": "notesnook",
      "name": "Notesnook",
      "website": "notesnook.com/",
      "description": "Open-source and end-to-end encrypted notes with desktop and mobile clients",
      "repo_url": "github.com/streetwriters/notesnook-sync-server",
      "repo_key": "github.com/streetwriters/notesnook-sync-server",
      "stars": null,
      "forks": 0,
      "updated_at": "2",
      "license": null,
      "tags": [
        "Note-Taking"
      ],
      "readme_path": "knowledge/readmes/github.com__streetwriters__notesnook-sync-server.md",
      "readme_status": "not_modified",
      "provenance": {
        "source": "selfhst/cdn directory/software.json",
        "fetched_at": "2026-03-04T17:40:41Z",
        "row_hash": "880d30e982147ba675d3a836d81f3067f36da2842a2227eebff2df6e8db9b2ea"
      }
    },
    {
      "reference": "notifiarr",
      "name": "Notifiarr",
      "website": "notifiarr.wiki",
      "description": "Monitoring and notifications via Discord",
      "repo_url": "github.com/Notifiarr/notifiarr",
      "repo_key": "github.com/Notifiarr/notifiarr",
      "stars": null,
      "forks": 15,
      "updated_at": "15",
      "license": null,
      "tags": [
        "Monitoring",
        "Notifications",
        "Server Management"
      ],
      "readme_path": "knowledge/readmes/github.com__Notifiarr__notifiarr.md",
      "readme_status": "not_modified",
      "provenance": {
        "source": "selfhst/cdn directory/software.json",
        "fetched_at": "2026-03-04T17:40:41Z",
        "row_hash": "04a68a3e0d4d9d0fa3c26646ca08a857cc9bb13303a448dbc7bf3b89c8b8602b"
      }
    },
    {
      "reference": "notifuse",
      "name": "Notifuse",
      "website": "www.notifuse.com",
      "description": "Platform for sending newsletters and transactional mail",
      "repo_url": "github.com/Notifuse/notifuse",
      "repo_key": "github.com/Notifuse/notifuse",
      "stars": null,
      "forks": 8,
      "updated_at": "15",
      "license": null,
      "tags": [
        "Email",
        "Newsletters"
      ],
      "readme_path": "knowledge/readmes/github.com__Notifuse__notifuse.md",
      "readme_status": "not_modified",
      "provenance": {
        "source": "selfhst/cdn directory/software.json",
        "fetched_at": "2026-03-04T17:40:41Z",
        "row_hash": "5ef9d003da1f88cf64fa0daa5c75b7b460aa5b13b8d2c6d6bae873ecaf4862cc"
      }
    },
    {
      "reference": "novu",
      "name": "Novu",
      "website": "go.novu.co/github",
      "description": "Open source notifications framework",
      "repo_url": "github.com/novuhq/novu",
      "repo_key": "github.com/novuhq/novu",
      "stars": null,
      "forks": 8,
      "updated_at": "41",
      "license": null,
      "tags": [
        "Development",
        "Notifications"
      ],
      "readme_path": "knowledge/readmes/github.com__novuhq__novu.md",
      "readme_status": "not_modified",
      "provenance": {
        "source": "selfhst/cdn directory/software.json",
        "fetched_at": "2026-03-04T17:40:41Z",
        "row_hash": "ba566cb39939b923012584fd9e1a73134c3ac6cfc3b2aab11a8a33a20479bade"
      }
    },
    {
      "reference": "npmplus",
      "name": "NPMplus",
      "website": "github.com/ZoeyVid/NPMplus",
      "description": "Nginx Proxy Manager with improvements",
      "repo_url": "github.com/ZoeyVid/NPMplus",
      "repo_key": "github.com/ZoeyVid/NPMplus",
      "stars": null,
      "forks": 15,
      "updated_at": "41",
      "license": null,
      "tags": [
        "Reverse Proxy",
        "Web Server"
      ],
      "readme_path": "knowledge/readmes/github.com__ZoeyVid__NPMplus.md",
      "readme_status": "not_modified",
      "provenance": {
        "source": "selfhst/cdn directory/software.json",
        "fetched_at": "2026-03-04T17:40:41Z",
        "row_hash": "70a6766af986ac401cd0a280ac9d2f24097ba78c324e3daabe631a31a123dd62"
      }
    },
    {
      "reference": "ntfy",
      "name": "ntfy",
      "website": "ntfy.sh",
      "description": "Simple HTTP-based pub-sub notification service",
      "repo_url": "github.com/binwiederhier/ntfy",
      "repo_key": "github.com/binwiederhier/ntfy",
      "stars": null,
      "forks": 1,
      "updated_at": "15",
      "license": null,
      "tags": [
        "Notifications"
      ],
      "readme_path": "knowledge/readmes/github.com__binwiederhier__ntfy.md",
      "readme_status": "not_modified",
      "provenance": {
        "source": "selfhst/cdn directory/software.json",
        "fetched_at": "2026-03-04T17:40:41Z",
        "row_hash": "5fe63a556c491b2824794dfdfa6e546985834ad7c9f09c9bee5c1bc3d4d3e726"
      }
    },
    {
      "reference": "nutify",
      "name": "Nutify",
      "website": "github.com/DartSteven/Nutify",
      "description": "Modern web-based UPS monitoring",
      "repo_url": "github.com/DartSteven/Nutify",
      "repo_key": "github.com/DartSteven/Nutify",
      "stars": null,
      "forks": 8,
      "updated_at": "31",
      "license": null,
      "tags": [
        "Monitoring"
      ],
      "readme_path": "knowledge/readmes/github.com__DartSteven__Nutify.md",
      "readme_status": "not_modified",
      "provenance": {
        "source": "selfhst/cdn directory/software.json",
        "fetched_at": "2026-03-04T17:40:41Z",
        "row_hash": "2864e05f7678bdc90f825ae8e838223f7c6a9514b6cc2ff605c47b2d1837f909"
      }
    },
    {
      "reference": "nzb-dav",
      "name": "Nzb DAV",
      "website": "github.com/nzbdav-dev/nzbdav",
      "description": "Virtually mount NZB files for direct streaming",
      "repo_url": "github.com/nzbdav-dev/nzbdav",
      "repo_key": "github.com/nzbdav-dev/nzbdav",
      "stars": null,
      "forks": 15,
      "updated_at": "2",
      "license": null,
      "tags": [
        "Downloads",
        "Media Streaming"
      ],
      "readme_path": "knowledge/readmes/github.com__nzbdav-dev__nzbdav.md",
      "readme_status": "not_modified",
      "provenance": {
        "source": "selfhst/cdn directory/software.json",
        "fetched_at": "2026-03-04T17:40:41Z",
        "row_hash": "41a641534bfc430ffd548b5246f79608acbbcf32162b605a1a872dd964713575"
      }
    },
    {
      "reference": "nzbget",
      "name": "NZBGet",
      "website": "nzbget.com",
      "description": "Fast, reliable, and feature-packed NZB downloader",
      "repo_url": "github.com/nzbgetcom/nzbget",
      "repo_key": "github.com/nzbgetcom/nzbget",
      "stars": null,
      "forks": 10,
      "updated_at": "3",
      "license": null,
      "tags": [
        "Downloads"
      ],
      "readme_path": "knowledge/readmes/github.com__nzbgetcom__nzbget.md",
      "readme_status": "not_modified",
      "provenance": {
        "source": "selfhst/cdn directory/software.json",
        "fetched_at": "2026-03-04T17:40:41Z",
        "row_hash": "64e4eb669e01074622a66921cd403739e44918a273a7c67eb9ca771c561ab89b"
      }
    },
    {
      "reference": "oauth2-proxy",
      "name": "OAuth2 Proxy",
      "website": "oauth2-proxy.github.io/oauth2-proxy",
      "description": "Reverse proxy and authentication middleware",
      "repo_url": "github.com/oauth2-proxy/oauth2-proxy",
      "repo_key": "github.com/oauth2-proxy/oauth2-proxy",
      "stars": null,
      "forks": 15,
      "updated_at": "15",
      "license": null,
      "tags": [
        "Authentication",
        "Reverse Proxy"
      ],
      "readme_path": "knowledge/readmes/github.com__oauth2-proxy__oauth2-proxy.md",
      "readme_status": "not_modified",
      "provenance": {
        "source": "selfhst/cdn directory/software.json",
        "fetched_at": "2026-03-04T17:40:41Z",
        "row_hash": "1053b9b2e3f30a756ba9ced069850d9a9a97bf7796090b4bfa5d82d5815d8d07"
      }
    },
    {
      "reference": "obico",
      "name": "Obico",
      "website": "obico.io",
      "description": "Smart 3D printing platform with AI failure detection",
      "repo_url": "github.com/TheSpaghettiDetective/obico-server",
      "repo_key": "github.com/TheSpaghettiDetective/obico-server",
      "stars": null,
      "forks": 0,
      "updated_at": "43",
      "license": null,
      "tags": [
        "3D Printing"
      ],
      "readme_path": "knowledge/readmes/github.com__TheSpaghettiDetective__obico-server.md",
      "readme_status": "not_modified",
      "provenance": {
        "source": "selfhst/cdn directory/software.json",
        "fetched_at": "2026-03-04T17:40:41Z",
        "row_hash": "c9f508eed835eb5ba33f557b37b0b133bf1c8e1aecdfe7978b65e03e8c636f74"
      }
    },
    {
      "reference": "obsidian-livesync",
      "name": "Obsidian LiveSync",
      "website": "github.com/vrtmrz/obsidian-livesync",
      "description": "Community-implemented sync plugin for Obsidian",
      "repo_url": "github.com/vrtmrz/obsidian-livesync",
      "repo_key": "github.com/vrtmrz/obsidian-livesync",
      "stars": null,
      "forks": 15,
      "updated_at": "41",
      "license": null,
      "tags": [
        "File Transfer and Sync",
        "Note-Taking",
        "Wiki"
      ],
      "readme_path": "knowledge/readmes/github.com__vrtmrz__obsidian-livesync.md",
      "readme_status": "not_modified",
      "provenance": {
        "source": "selfhst/cdn directory/software.json",
        "fetched_at": "2026-03-04T17:40:41Z",
        "row_hash": "049827828e3d3481be82e27bd0253fd1b637d94f68368335a7388fb94253bfc0"
      }
    },
    {
      "reference": "obskurnee",
      "name": "Obskurnee",
      "website": "github.com/zblesk/obskurnee",
      "description": "Book club companion for voting on upcoming books",
      "repo_url": "github.com/zblesk/obskurnee",
      "repo_key": "github.com/zblesk/obskurnee",
      "stars": null,
      "forks": 8,
      "updated_at": "2",
      "license": null,
      "tags": [
        "Books",
        "Voting"
      ],
      "readme_path": "knowledge/readmes/github.com__zblesk__obskurnee.md",
      "readme_status": "not_modified",
      "provenance": {
        "source": "selfhst/cdn directory/software.json",
        "fetched_at": "2026-03-04T17:40:41Z",
        "row_hash": "fba88ae51ff8cb6b393c19aa061da75b46e3dfa29676b73841de4f0ac960c68e"
      }
    },
    {
      "reference": "octelium",
      "name": "Octelium",
      "website": "octelium.com/docs",
      "description": "Unified zero trust secure access platform",
      "repo_url": "github.com/octelium/octelium",
      "repo_key": "github.com/octelium/octelium",
      "stars": null,
      "forks": 0,
      "updated_at": "15",
      "license": null,
      "tags": [
        "Authentication",
        "Remote Access",
        "VPN"
      ],
      "readme_path": "knowledge/readmes/github.com__octelium__octelium.md",
      "readme_status": "not_modified",
      "provenance": {
        "source": "selfhst/cdn directory/software.json",
        "fetched_at": "2026-03-04T17:40:41Z",
        "row_hash": "51347737d59d2c127a3ede03cb8604412fb2f848fc69c5f5c6b445a3d217fda0"
      }
    },
    {
      "reference": "octelium",
      "name": "Octelium",
      "website": "octelium.com/docs",
      "description": "Unified zero-trust secure access platform",
      "repo_url": "github.com/octelium/octelium",
      "repo_key": "github.com/octelium/octelium",
      "stars": null,
      "forks": 0,
      "updated_at": "15",
      "license": null,
      "tags": [
        "Authentication",
        "Remote Access",
        "VPN"
      ],
      "readme_path": "knowledge/readmes/github.com__octelium__octelium.md",
      "readme_status": "not_modified",
      "provenance": {
        "source": "selfhst/cdn directory/software.json",
        "fetched_at": "2026-03-04T17:40:41Z",
        "row_hash": "12eb7c11b255d3278f1604f2cef11bef1a93174109b6a89b4f61e6f5cb19b495"
      }
    },
    {
      "reference": "octo-fiesta",
      "name": "Octo-Fiesta",
      "website": "github.com/V1ck3s/octo-fiesta",
      "description": "Subsonic proxy for integrating streaming providers as music sources",
      "repo_url": "github.com/V1ck3s/octo-fiesta",
      "repo_key": "github.com/V1ck3s/octo-fiesta",
      "stars": null,
      "forks": 11,
      "updated_at": "2",
      "license": null,
      "tags": [
        "Music",
        "Music Streaming"
      ],
      "readme_path": "knowledge/readmes/github.com__V1ck3s__octo-fiesta.md",
      "readme_status": "not_modified",
      "provenance": {
        "source": "selfhst/cdn directory/software.json",
        "fetched_at": "2026-03-04T17:40:41Z",
        "row_hash": "54494786436f43d18990003aa7f682f17d0bc8356acd9d09848461ea9203a7f7"
      }
    },
    {
      "reference": "octoprint",
      "name": "OctoPrint",
      "website": "octoprint.org",
      "description": "Snappy web interface for your 3D printer",
      "repo_url": "github.com/OctoPrint/OctoPrint",
      "repo_key": "github.com/OctoPrint/OctoPrint",
      "stars": null,
      "forks": 0,
      "updated_at": "31",
      "license": null,
      "tags": [
        "3D Printing"
      ],
      "readme_path": "knowledge/readmes/github.com__OctoPrint__OctoPrint.md",
      "readme_status": "not_modified",
      "provenance": {
        "source": "selfhst/cdn directory/software.json",
        "fetched_at": "2026-03-04T17:40:41Z",
        "row_hash": "52396f68ff78c6582d4aae79bfe4b16233366a74387bf452ed12facd28c9e8d0"
      }
    },
    {
      "reference": "ocular",
      "name": "Ocular",
      "website": "simonwep.github.io/ocular",
      "description": "Simple, beautiful budgeting app",
      "repo_url": "github.com/simonwep/ocular",
      "repo_key": "github.com/simonwep/ocular",
      "stars": null,
      "forks": 15,
      "updated_at": "43",
      "license": null,
      "tags": [
        "Budgeting"
      ],
      "readme_path": "knowledge/readmes/github.com__simonwep__ocular.md",
      "readme_status": "not_modified",
      "provenance": {
        "source": "selfhst/cdn directory/software.json",
        "fetched_at": "2026-03-04T17:40:41Z",
        "row_hash": "e362744ffa5bf039c32a657a3048aa83aba06a0fa2e0665c0b2468dc8e95e8dd"
      }
    },
    {
      "reference": "odoo",
      "name": "Odoo",
      "website": "www.odoo.com",
      "description": "Suite of open-source business apps",
      "repo_url": "github.com/odoo/odoo",
      "repo_key": "github.com/odoo/odoo",
      "stars": null,
      "forks": 8,
      "updated_at": "31",
      "license": null,
      "tags": [
        "Accounting",
        "Customer Engagement",
        "Customer Relationship Management"
      ],
      "readme_path": "knowledge/readmes/github.com__odoo__odoo.md",
      "readme_status": "not_modified",
      "provenance": {
        "source": "selfhst/cdn directory/software.json",
        "fetched_at": "2026-03-04T17:40:41Z",
        "row_hash": "0877d3c634c07c82aa90f2d5cc4fec8647927a657aef7240f71603ac186136ae"
      }
    },
    {
      "reference": "olivetin",
      "name": "OliveTin",
      "website": "olivetin.app",
      "description": "Safe and simple access to pre-defined shell commands from a web interface",
      "repo_url": "github.com/OliveTin/OliveTin",
      "repo_key": "github.com/OliveTin/OliveTin",
      "stars": null,
      "forks": 0,
      "updated_at": "15",
      "license": null,
      "tags": [
        "Remote Access"
      ],
      "readme_path": "knowledge/readmes/github.com__OliveTin__OliveTin.md",
      "readme_status": "not_modified",
      "provenance": {
        "source": "selfhst/cdn directory/software.json",
        "fetched_at": "2026-03-04T17:40:41Z",
        "row_hash": "fbc52104fc434e587c35cc4be81c8bb7b4381b38d8f98deb9cc2028524665f1d"
      }
    },
    {
      "reference": "ombi",
      "name": "Ombi",
      "website": "http://ombi.io",
      "description": "Friendly media request tool with media server sync support",
      "repo_url": "github.com/Ombi-app/Ombi",
      "repo_key": "github.com/Ombi-app/Ombi",
      "stars": null,
      "forks": 10,
      "updated_at": "2",
      "license": null,
      "tags": [
        "Requests"
      ],
      "readme_path": "knowledge/readmes/github.com__Ombi-app__Ombi.md",
      "readme_status": "not_modified",
      "provenance": {
        "source": "selfhst/cdn directory/software.json",
        "fetched_at": "2026-03-04T17:40:41Z",
        "row_hash": "8833e1f0953405b5e52a11d1e212863209796ed10da6fba249da13dbecdc7763"
      }
    },
    {
      "reference": "omnipoly",
      "name": "OmniPoly",
      "website": "github.com/kWeglinski/OmniPoly",
      "description": "Frontend for LanguageTool and LibreTranslate with AI translation",
      "repo_url": "github.com/kWeglinski/OmniPoly",
      "repo_key": "github.com/kWeglinski/OmniPoly",
      "stars": null,
      "forks": 11,
      "updated_at": "19",
      "license": null,
      "tags": [
        "Front End",
        "Language"
      ],
      "readme_path": "knowledge/readmes/github.com__kWeglinski__OmniPoly.md",
      "readme_status": "not_modified",
      "provenance": {
        "source": "selfhst/cdn directory/software.json",
        "fetched_at": "2026-03-04T17:40:41Z",
        "row_hash": "5e84a1da402382b296b2eae19ad7e753587d9c8d157d7eca6f824dcd80d8a252"
      }
    },
    {
      "reference": "omnitools",
      "name": "OmniTools",
      "website": "omnitools.app",
      "description": "Online tools for simplifying everyday tasks",
      "repo_url": "github.com/iib0011/omni-tools",
      "repo_key": "github.com/iib0011/omni-tools",
      "stars": null,
      "forks": 15,
      "updated_at": "41",
      "license": null,
      "tags": [
        "Tools"
      ],
      "readme_path": "knowledge/readmes/github.com__iib0011__omni-tools.md",
      "readme_status": "not_modified",
      "provenance": {
        "source": "selfhst/cdn directory/software.json",
        "fetched_at": "2026-03-04T17:40:41Z",
        "row_hash": "4b310c521b0de02322ce048f4b25582b94c10176b1f82eadcf153c9c13418e92"
      }
    },
    {
      "reference": "omoide",
      "name": "Omoide",
      "website": "github.com/EinAeffchen/Omoide",
      "description": "Photo and video library with AI features",
      "repo_url": "github.com/EinAeffchen/Omoide",
      "repo_key": "github.com/EinAeffchen/Omoide",
      "stars": null,
      "forks": 8,
      "updated_at": "41",
      "license": null,
      "tags": [
        "Photos",
        "Videos"
      ],
      "readme_path": "knowledge/readmes/github.com__EinAeffchen__Omoide.md",
      "readme_status": "not_modified",
      "provenance": {
        "source": "selfhst/cdn directory/software.json",
        "fetched_at": "2026-03-04T17:40:41Z",
        "row_hash": "60997651843ef56ea8052f4614da56c3a520b66755f423b90fee95ae3f2f8b0e"
      }
    },
    {
      "reference": "onedev",
      "name": "OneDev",
      "website": "onedev.io",
      "description": "Git server with CI/CD, kanban, and packages",
      "repo_url": "github.com/theonedev/onedev",
      "repo_key": "github.com/theonedev/onedev",
      "stars": null,
      "forks": 15,
      "updated_at": "20",
      "license": null,
      "tags": [
        "Development",
        "Git"
      ],
      "readme_path": "knowledge/readmes/github.com__theonedev__onedev.md",
      "readme_status": "not_modified",
      "provenance": {
        "source": "selfhst/cdn directory/software.json",
        "fetched_at": "2026-03-04T17:40:41Z",
        "row_hash": "bdc98892359dba369e0080dc309e00d36a9780021e07170b68d5de4636d091f9"
      }
    },
    {
      "reference": "oneuptime",
      "name": "OneUptime",
      "website": "oneuptime.com",
      "description": "Complete open-source observability platform",
      "repo_url": "github.com/OneUptime/oneuptime",
      "repo_key": "github.com/OneUptime/oneuptime",
      "stars": null,
      "forks": 1,
      "updated_at": "41",
      "license": null,
      "tags": [
        "Monitoring",
        "Uptime"
      ],
      "readme_path": "knowledge/readmes/github.com__OneUptime__oneuptime.md",
      "readme_status": "not_modified",
      "provenance": {
        "source": "selfhst/cdn directory/software.json",
        "fetched_at": "2026-03-04T17:40:41Z",
        "row_hash": "1ce9b97be431d602292071aff52f177dc8def9351127e934946470eceaa4a86c"
      }
    },
    {
      "reference": "ontime",
      "name": "Ontime",
      "website": "www.getontime.no",
      "description": "Timers for event rundowns, scheduling, and cueing",
      "repo_url": "github.com/cpvalente/ontime",
      "repo_key": "github.com/cpvalente/ontime",
      "stars": null,
      "forks": 8,
      "updated_at": "41",
      "license": null,
      "tags": [
        "Events",
        "Tracking"
      ],
      "readme_path": "knowledge/readmes/github.com__cpvalente__ontime.md",
      "readme_status": "not_modified",
      "provenance": {
        "source": "selfhst/cdn directory/software.json",
        "fetched_at": "2026-03-04T17:40:41Z",
        "row_hash": "c949448fe409f5ad98345575b70bce1a6b99bf89a3892d8a43f1d9d9af36f629"
      }
    },
    {
      "reference": "open-archiver",
      "name": "Open Archiver",
      "website": "openarchiver.com",
      "description": "Archive, store, and index email from major platforms",
      "repo_url": "github.com/LogicLabs-OU/OpenArchiver",
      "repo_key": "github.com/LogicLabs-OU/OpenArchiver",
      "stars": null,
      "forks": 0,
      "updated_at": "41",
      "license": null,
      "tags": [
        "Archive",
        "Email"
      ],
      "readme_path": "knowledge/readmes/github.com__LogicLabs-OU__OpenArchiver.md",
      "readme_status": "not_modified",
      "provenance": {
        "source": "selfhst/cdn directory/software.json",
        "fetched_at": "2026-03-04T17:40:41Z",
        "row_hash": "090836ce6c10134c814651a39faae04076d058d2ae2f5b26029e83e988076982"
      }
    },
    {
      "reference": "open-web-analytics",
      "name": "Open Web Analytics",
      "website": "http://www.openwebanalytics.com",
      "description": "Open-source alternative to commercial web analytics tools like Google Analytics",
      "repo_url": "github.com/Open-Web-Analytics/Open-Web-Analytics",
      "repo_key": "github.com/Open-Web-Analytics/Open-Web-Analytics",
      "stars": null,
      "forks": 10,
      "updated_at": "28",
      "license": null,
      "tags": [
        "Web Analytics"
      ],
      "readme_path": "knowledge/readmes/github.com__Open-Web-Analytics__Open-Web-Analytics.md",
      "readme_status": "not_modified",
      "provenance": {
        "source": "selfhst/cdn directory/software.json",
        "fetched_at": "2026-03-04T17:40:41Z",
        "row_hash": "9d5e214823ff335329abe959eea30ddf9d4646cb16fc2204cddc5beb000c4544"
      }
    },
    {
      "reference": "open-webui",
      "name": "Open WebUI",
      "website": "openwebui.com",
      "description": "User-friendly and extensible AI interface",
      "repo_url": "github.com/open-webui/open-webui",
      "repo_key": "github.com/open-webui/open-webui",
      "stars": null,
      "forks": 8,
      "updated_at": "31",
      "license": null,
      "tags": [
        "Artificial Intelligence",
        "Front End"
      ],
      "readme_path": "knowledge/readmes/github.com__open-webui__open-webui.md",
      "readme_status": "not_modified",
      "provenance": {
        "source": "selfhst/cdn directory/software.json",
        "fetched_at": "2026-03-04T17:40:41Z",
        "row_hash": "9e28b7994538c47f861f6c6be32926a61265b353630fdb2efde8e36bf37605ad"
      }
    },
    {
      "reference": "openbao",
      "name": "OpenBao",
      "website": "openbao.org/",
      "description": "Sensitive data store for secrets, certificates, and keys",
      "repo_url": "github.com/openbao/openbao",
      "repo_key": "github.com/openbao/openbao",
      "stars": null,
      "forks": 16,
      "updated_at": "15",
      "license": null,
      "tags": [
        "Password Manager"
      ],
      "readme_path": "knowledge/readmes/github.com__openbao__openbao.md",
      "readme_status": "not_modified",
      "provenance": {
        "source": "selfhst/cdn directory/software.json",
        "fetched_at": "2026-03-04T17:40:41Z",
        "row_hash": "b06025814c910d79ac0ef217f322fb452464b9c9e69fde2429ed76049734cd73"
      }
    },
    {
      "reference": "openbudgeteer",
      "name": "OpenBudgeteer",
      "website": "axelander.dev",
      "description": "Budgeting app based on the bucket budgeting principle",
      "repo_url": "github.com/TheAxelander/OpenBudgeteer",
      "repo_key": "github.com/TheAxelander/OpenBudgeteer",
      "stars": null,
      "forks": 0,
      "updated_at": "2",
      "license": null,
      "tags": [
        "Budgeting"
      ],
      "readme_path": "knowledge/readmes/github.com__TheAxelander__OpenBudgeteer.md",
      "readme_status": "not_modified",
      "provenance": {
        "source": "selfhst/cdn directory/software.json",
        "fetched_at": "2026-03-04T17:40:41Z",
        "row_hash": "20bffa24497cd83121ea3c097ac7ddc46f7bfa97453e96cbcae52c175fbf053d"
      }
    },
    {
      "reference": "openchangelog",
      "name": "Openchangelog",
      "website": "openchangelog.com",
      "description": "Easy to configure and self-hostable changelog website",
      "repo_url": "github.com/JonasHiltl/openchangelog",
      "repo_key": "github.com/JonasHiltl/openchangelog",
      "stars": null,
      "forks": 0,
      "updated_at": "15",
      "license": null,
      "tags": [
        "Development"
      ],
      "readme_path": "knowledge/readmes/github.com__JonasHiltl__openchangelog.md",
      "readme_status": "not_modified",
      "provenance": {
        "source": "selfhst/cdn directory/software.json",
        "fetched_at": "2026-03-04T17:40:41Z",
        "row_hash": "62d096c5db76f4d1e7c46154fd608ba9a9181ca93ce2424ca025c7ae449bc8f3"
      }
    },
    {
      "reference": "opencloud",
      "name": "OpenCloud",
      "website": "opencloud.eu",
      "description": "Secure and private app for storing, accessing, and sharing files",
      "repo_url": "github.com/opencloud-eu/opencloud",
      "repo_key": "github.com/opencloud-eu/opencloud",
      "stars": null,
      "forks": 1,
      "updated_at": "15",
      "license": null,
      "tags": [
        "Cloud Storage",
        "File Sharing"
      ],
      "readme_path": "knowledge/readmes/github.com__opencloud-eu__opencloud.md",
      "readme_status": "not_modified",
      "provenance": {
        "source": "selfhst/cdn directory/software.json",
        "fetched_at": "2026-03-04T17:40:41Z",
        "row_hash": "9d55df022e61ab3bab2755e1bb18d13f9af182da092698986f2fcae87ef668ef"
      }
    },
    {
      "reference": "opencut",
      "name": "OpenCut",
      "website": "opencut.app",
      "description": "Video editor for web, desktop, and mobile",
      "repo_url": "github.com/OpenCut-app/OpenCut",
      "repo_key": "github.com/OpenCut-app/OpenCut",
      "stars": null,
      "forks": 15,
      "updated_at": "41",
      "license": null,
      "tags": [
        "Video Editing"
      ],
      "readme_path": "knowledge/readmes/github.com__OpenCut-app__OpenCut.md",
      "readme_status": "not_modified",
      "provenance": {
        "source": "selfhst/cdn directory/software.json",
        "fetched_at": "2026-03-04T17:40:41Z",
        "row_hash": "f64487eb3dc2e04ef46385d2b8f7806b95db1e6d3bf16c3c05bcd3372682b660"
      }
    },
    {
      "reference": "openemr",
      "name": "OpenEMR",
      "website": "open-emr.org/",
      "description": "Open-source electronic health records",
      "repo_url": "github.com/openemr/openemr",
      "repo_key": "github.com/openemr/openemr",
      "stars": null,
      "forks": 11,
      "updated_at": "28",
      "license": null,
      "tags": [
        "Medical"
      ],
      "readme_path": "knowledge/readmes/github.com__openemr__openemr.md",
      "readme_status": "not_modified",
      "provenance": {
        "source": "selfhst/cdn directory/software.json",
        "fetched_at": "2026-03-04T17:40:41Z",
        "row_hash": "9b5ef652ea953b206161993abe28344c15487a49339e445b19281c02043db5cb"
      }
    },
    {
      "reference": "opengist",
      "name": "Opengist",
      "website": "opengist.io",
      "description": "Self-hosted pastebin powered by Git",
      "repo_url": "github.com/thomiceli/opengist",
      "repo_key": "github.com/thomiceli/opengist",
      "stars": null,
      "forks": 0,
      "updated_at": "15",
      "license": null,
      "tags": [
        "Pastebin"
      ],
      "readme_path": "knowledge/readmes/github.com__thomiceli__opengist.md",
      "readme_status": "not_modified",
      "provenance": {
        "source": "selfhst/cdn directory/software.json",
        "fetched_at": "2026-03-04T17:40:41Z",
        "row_hash": "40338e684606bfc38772803615854a89847e2067f91d7143cca0a209e4add3a4"
      }
    },
    {
      "reference": "openpanel",
      "name": "OpenPanel",
      "website": "openpanel.com",
      "description": "Powerful and flexible web hosting control panel for Linux",
      "repo_url": "github.com/stefanpejcic/OpenPanel",
      "repo_key": "github.com/stefanpejcic/OpenPanel",
      "stars": null,
      "forks": 8,
      "updated_at": "41",
      "license": null,
      "tags": [
        "Control Panel"
      ],
      "readme_path": "knowledge/readmes/github.com__stefanpejcic__OpenPanel.md",
      "readme_status": "not_modified",
      "provenance": {
        "source": "selfhst/cdn directory/software.json",
        "fetched_at": "2026-03-04T17:40:41Z",
        "row_hash": "2273217d0ecd494f6d8a036391e28577299dec79e05008af87a3e4f9301a5662"
      }
    },
    {
      "reference": "openproject",
      "name": "OpenProject",
      "website": "www.openproject.org",
      "description": "Web-based project management software",
      "repo_url": "github.com/opf/openproject",
      "repo_key": "github.com/opf/openproject",
      "stars": null,
      "forks": 11,
      "updated_at": "32",
      "license": null,
      "tags": [
        "Kanban",
        "Project Management"
      ],
      "readme_path": "knowledge/readmes/github.com__opf__openproject.md",
      "readme_status": "not_modified",
      "provenance": {
        "source": "selfhst/cdn directory/software.json",
        "fetched_at": "2026-03-04T17:40:41Z",
        "row_hash": "eba1e55cadb9828d2b3a6a2747a7f449db07645f02ec49f5dd63c8dc5b8c9eea"
      }
    },
    {
      "reference": "openreads",
      "name": "Openreads",
      "website": "github.com/mateusz-bak/openreads",
      "description": "Privacy-oriented and cross-platform book tracking app",
      "repo_url": "github.com/mateusz-bak/openreads",
      "repo_key": "github.com/mateusz-bak/openreads",
      "stars": null,
      "forks": 10,
      "updated_at": "7",
      "license": null,
      "tags": [
        "Android",
        "Books",
        "iOS"
      ],
      "readme_path": "knowledge/readmes/github.com__mateusz-bak__openreads.md",
      "readme_status": "not_modified",
      "provenance": {
        "source": "selfhst/cdn directory/software.json",
        "fetched_at": "2026-03-04T17:40:41Z",
        "row_hash": "f6121f00ae8a08ba76610366b9817089e8d945d9c921ca01944ee3deeb8483aa"
      }
    },
    {
      "reference": "opensign",
      "name": "OpenSign",
      "website": "www.opensignlabs.com",
      "description": "The open-source document e-signing solution",
      "repo_url": "github.com/OpenSignLabs/OpenSign",
      "repo_key": "github.com/OpenSignLabs/OpenSign",
      "stars": null,
      "forks": 8,
      "updated_at": "21",
      "license": null,
      "tags": [
        "Document Signing"
      ],
      "readme_path": "knowledge/readmes/github.com__OpenSignLabs__OpenSign.md",
      "readme_status": "not_modified",
      "provenance": {
        "source": "selfhst/cdn directory/software.json",
        "fetched_at": "2026-03-04T17:40:41Z",
        "row_hash": "2baa5b3048c63d66c367822840d39af5349b013472136996d3d90e3bc6bc94c4"
      }
    }
  ]
}