{
  "chunk": 21,
  "count": 50,
  "generated_at": "2026-04-26T05:45:46Z",
  "items": [
    {
      "reference": "shlink",
      "name": "Shlink",
      "website": "shlink.io",
      "description": "The definitive self-hosted URL shortener",
      "repo_url": "github.com/shlinkio/shlink",
      "repo_key": "github.com/shlinkio/shlink",
      "stars": null,
      "forks": 15,
      "updated_at": "26",
      "license": null,
      "tags": [
        "URL Shortener"
      ],
      "readme_path": "knowledge/readmes/github.com__shlinkio__shlink.md",
      "readme_status": "not_modified",
      "provenance": {
        "source": "selfhst/cdn directory/software.json",
        "fetched_at": "2026-04-26T05:38:19Z",
        "row_hash": "de78204582609d2dc3c775a47052dd9b96406251026f4b470aad5fcc01fc83bd"
      }
    },
    {
      "reference": "shotshare",
      "name": "ShotShare",
      "website": "github.com/mdshack/shotshare",
      "description": "Open source image sharing application",
      "repo_url": "github.com/mdshack/shotshare",
      "repo_key": "github.com/mdshack/shotshare",
      "stars": null,
      "forks": 15,
      "updated_at": "26",
      "license": null,
      "tags": [
        "Image Sharing",
        "Photos"
      ],
      "readme_path": "knowledge/readmes/github.com__mdshack__shotshare.md",
      "readme_status": "not_modified",
      "provenance": {
        "source": "selfhst/cdn directory/software.json",
        "fetched_at": "2026-04-26T05:38:19Z",
        "row_hash": "ea0e7914b3771dbf909fe12168399a89b819317c09a0307bb314ab541fb8f7fe"
      }
    },
    {
      "reference": "signature-pdf",
      "name": "Signature PDF",
      "website": "pdf.24eme.fr",
      "description": "Sign, organize, edit, and compress PDF files",
      "repo_url": "github.com/24eme/signaturepdf",
      "repo_key": "github.com/24eme/signaturepdf",
      "stars": null,
      "forks": 0,
      "updated_at": "20",
      "license": null,
      "tags": [
        "PDF"
      ],
      "readme_path": "knowledge/readmes/github.com__24eme__signaturepdf.md",
      "readme_status": "not_modified",
      "provenance": {
        "source": "selfhst/cdn directory/software.json",
        "fetched_at": "2026-04-26T05:38:19Z",
        "row_hash": "9c51ee817655320f426eb41ff0c4734818df487b3cc3394e5eb0b2ddc0e280fd"
      }
    },
    {
      "reference": "signoz",
      "name": "SigNoz",
      "website": "signoz.io",
      "description": "Logs, metrics, and traces in a single pane",
      "repo_url": "github.com/SigNoz/signoz",
      "repo_key": "github.com/SigNoz/signoz",
      "stars": null,
      "forks": 8,
      "updated_at": "38",
      "license": null,
      "tags": [
        "Monitoring"
      ],
      "readme_path": "knowledge/readmes/github.com__SigNoz__signoz.md",
      "readme_status": "not_modified",
      "provenance": {
        "source": "selfhst/cdn directory/software.json",
        "fetched_at": "2026-04-26T05:38:19Z",
        "row_hash": "6bc44f4b01a5df8a15690d2bc5d925c82976b3013a15fbf4b96566a491253181"
      }
    },
    {
      "reference": "silex",
      "name": "Silex",
      "website": "www.silex.me",
      "description": "No-code tool for building websites",
      "repo_url": "github.com/silexlabs/Silex",
      "repo_key": "github.com/silexlabs/Silex",
      "stars": null,
      "forks": 0,
      "updated_at": "20",
      "license": null,
      "tags": [
        "Development",
        "No-Code / Low-Code"
      ],
      "readme_path": "knowledge/readmes/github.com__silexlabs__Silex.md",
      "readme_status": "not_modified",
      "provenance": {
        "source": "selfhst/cdn directory/software.json",
        "fetched_at": "2026-04-26T05:38:19Z",
        "row_hash": "6758cc24d152c05b8356cc5831d1dd2faf239b542e9aa26f5efffdfb39dc8dce"
      }
    },
    {
      "reference": "silicon-notes",
      "name": "Silicon Notes",
      "website": "github.com/cu/silicon",
      "description": "Web-based personal knowledge base with few frills",
      "repo_url": "github.com/cu/silicon",
      "repo_key": "github.com/cu/silicon",
      "stars": null,
      "forks": 8,
      "updated_at": "29",
      "license": null,
      "tags": [
        "Note-Taking",
        "Wiki"
      ],
      "readme_path": "knowledge/readmes/github.com__cu__silicon.md",
      "readme_status": "not_modified",
      "provenance": {
        "source": "selfhst/cdn directory/software.json",
        "fetched_at": "2026-04-26T05:38:19Z",
        "row_hash": "0a5e13ace74053cda1d53636fad681f53f33afb349522b607ca278794c2a24f3"
      }
    },
    {
      "reference": "silverbullet",
      "name": "SilverBullet",
      "website": "silverbullet.md",
      "description": "Programmable personal knowledge management",
      "repo_url": "github.com/silverbulletmd/silverbullet",
      "repo_key": "github.com/silverbulletmd/silverbullet",
      "stars": null,
      "forks": 15,
      "updated_at": "38",
      "license": null,
      "tags": [
        "Note-Taking"
      ],
      "readme_path": "knowledge/readmes/github.com__silverbulletmd__silverbullet.md",
      "readme_status": "not_modified",
      "provenance": {
        "source": "selfhst/cdn directory/software.json",
        "fetched_at": "2026-04-26T05:38:19Z",
        "row_hash": "f7cf3f62ebc83160b57e2bad4d8fdb80cdecaf649e2f03ef498b91f9468b0a1d"
      }
    },
    {
      "reference": "simplelogin",
      "name": "SimpleLogin",
      "website": "simplelogin.io",
      "description": "Send and receive e-mails anonymously",
      "repo_url": "github.com/simple-login/app",
      "repo_key": "github.com/simple-login/app",
      "stars": null,
      "forks": 0,
      "updated_at": "29",
      "license": null,
      "tags": [
        "Email",
        "Privacy"
      ],
      "readme_path": "knowledge/readmes/github.com__simple-login__app.md",
      "readme_status": "not_modified",
      "provenance": {
        "source": "selfhst/cdn directory/software.json",
        "fetched_at": "2026-04-26T05:38:19Z",
        "row_hash": "57b1b969238ff53a7d1a9259238802675ebbc8d21fc5e2877d1ba440b59d0cf7"
      }
    },
    {
      "reference": "simplex-chat",
      "name": "SimpleX Chat",
      "website": "simplex.chat",
      "description": "Messaging network without user identifiers of any kind",
      "repo_url": "github.com/simplex-chat/simplex-chat",
      "repo_key": "github.com/simplex-chat/simplex-chat",
      "stars": null,
      "forks": 0,
      "updated_at": "17",
      "license": null,
      "tags": [
        "Messaging"
      ],
      "readme_path": "knowledge/readmes/github.com__simplex-chat__simplex-chat.md",
      "readme_status": "not_modified",
      "provenance": {
        "source": "selfhst/cdn directory/software.json",
        "fetched_at": "2026-04-26T05:38:19Z",
        "row_hash": "7a7188d6886e2d6c11ff28780138df8196c75ce697aae57bf1647c869c91e7e5"
      }
    },
    {
      "reference": "sink",
      "name": "Sink",
      "website": "Sink.Cool",
      "description": "Simple, speedy, secure link shortener with analytics and deployed with Cloudflare",
      "repo_url": "github.com/miantiao-me/Sink",
      "repo_key": "github.com/miantiao-me/Sink",
      "stars": null,
      "forks": 0,
      "updated_at": "39",
      "license": null,
      "tags": [
        "URL Shortener"
      ],
      "readme_path": "knowledge/readmes/github.com__miantiao-me__Sink.md",
      "readme_status": "not_modified",
      "provenance": {
        "source": "selfhst/cdn directory/software.json",
        "fetched_at": "2026-04-26T05:38:19Z",
        "row_hash": "935688ed661a653ab411c8fc8a151133462bab5c5857ef39ce2060df800ffe10"
      }
    },
    {
      "reference": "siyuan",
      "name": "SiYuan",
      "website": "b3log.org/siyuan",
      "description": "Privacy-first personal knowledge management software",
      "repo_url": "github.com/siyuan-note/siyuan",
      "repo_key": "github.com/siyuan-note/siyuan",
      "stars": null,
      "forks": 0,
      "updated_at": "38",
      "license": null,
      "tags": [
        "Note-Taking",
        "Wiki",
        "Workspace"
      ],
      "readme_path": "knowledge/readmes/github.com__siyuan-note__siyuan.md",
      "readme_status": "not_modified",
      "provenance": {
        "source": "selfhst/cdn directory/software.json",
        "fetched_at": "2026-04-26T05:38:19Z",
        "row_hash": "917d6982a5ec34fd6fca971f63797bdbe526bf745ce1e9ee98d0cdcbac303570"
      }
    },
    {
      "reference": "slash",
      "name": "Slash",
      "website": "github.com/yourselfhosted/slash",
      "description": "Open source link shortener and sharing app",
      "repo_url": "github.com/yourselfhosted/slash",
      "repo_key": "github.com/yourselfhosted/slash",
      "stars": null,
      "forks": 0,
      "updated_at": "38",
      "license": null,
      "tags": [
        "URL Shortener"
      ],
      "readme_path": "knowledge/readmes/github.com__yourselfhosted__slash.md",
      "readme_status": "not_modified",
      "provenance": {
        "source": "selfhst/cdn directory/software.json",
        "fetched_at": "2026-04-26T05:38:19Z",
        "row_hash": "8528712a6a2e65b729fe5127ccfe264a476f45ef260148d32af8de67064d9338"
      }
    },
    {
      "reference": "slink",
      "name": "Slink",
      "website": "docs.slinkapp.io",
      "description": "Self-hosted image sharing platform",
      "repo_url": "github.com/andrii-kryvoviaz/slink",
      "repo_key": "github.com/andrii-kryvoviaz/slink",
      "stars": null,
      "forks": 0,
      "updated_at": "26",
      "license": null,
      "tags": [
        "Image Sharing"
      ],
      "readme_path": "knowledge/readmes/github.com__andrii-kryvoviaz__slink.md",
      "readme_status": "not_modified",
      "provenance": {
        "source": "selfhst/cdn directory/software.json",
        "fetched_at": "2026-04-26T05:38:19Z",
        "row_hash": "d75e018eb8b2deaefeb77e38bd2a16a9c552a70e0d3224a4d21db543030b1684"
      }
    },
    {
      "reference": "slskd",
      "name": "slskd",
      "website": "slskd.org",
      "description": "Web app for the Soulseek file-sharing network",
      "repo_url": "github.com/slskd/slskd",
      "repo_key": "github.com/slskd/slskd",
      "stars": null,
      "forks": 0,
      "updated_at": "1",
      "license": null,
      "tags": [
        "Downloads",
        "Music"
      ],
      "readme_path": "knowledge/readmes/github.com__slskd__slskd.md",
      "readme_status": "not_modified",
      "provenance": {
        "source": "selfhst/cdn directory/software.json",
        "fetched_at": "2026-04-26T05:38:19Z",
        "row_hash": "0c1a1543e06df09feecc9a3c3f5cfd83d66d5bc1cdc5a497a7d298a5e3e1c174"
      }
    },
    {
      "reference": "smokeping",
      "name": "SmokePing",
      "website": "http://www.smokeping.org",
      "description": "Latency logging, graphing, and alerts",
      "repo_url": "github.com/oetiker/SmokePing",
      "repo_key": "github.com/oetiker/SmokePing",
      "stars": null,
      "forks": 10,
      "updated_at": "25",
      "license": null,
      "tags": [
        "Monitoring"
      ],
      "readme_path": "knowledge/readmes/github.com__oetiker__SmokePing.md",
      "readme_status": "not_modified",
      "provenance": {
        "source": "selfhst/cdn directory/software.json",
        "fetched_at": "2026-04-26T05:38:19Z",
        "row_hash": "be613a6cc0ff28805f356442e0dd92c054d553a74a8624a43e12af4f2125f59b"
      }
    },
    {
      "reference": "snac",
      "name": "Snac",
      "website": "codeberg.org/grunfink/snac2",
      "description": "Simple, minimalistic ActivityPub instance",
      "repo_url": "codeberg.org/grunfink/snac2",
      "repo_key": "codeberg.org/grunfink/snac2",
      "stars": null,
      "forks": 15,
      "updated_at": "0",
      "license": null,
      "tags": [
        "ActivityPub / Fediverse"
      ],
      "readme_path": null,
      "readme_status": "error",
      "provenance": {
        "source": "selfhst/cdn directory/software.json",
        "fetched_at": "2026-04-26T05:38:19Z",
        "row_hash": "f892424f4803acb134f317e37ef0639025b6d7f786d8783b4c5f301b819130ee"
      }
    },
    {
      "reference": "snapdrop",
      "name": "Snapdrop",
      "website": "snapdrop.net",
      "description": "Local file sharing via browser",
      "repo_url": "github.com/SnapDrop/snapdrop",
      "repo_key": "github.com/SnapDrop/snapdrop",
      "stars": null,
      "forks": 11,
      "updated_at": "20",
      "license": null,
      "tags": [
        "Local File Sharing"
      ],
      "readme_path": "knowledge/readmes/github.com__SnapDrop__snapdrop.md",
      "readme_status": "not_modified",
      "provenance": {
        "source": "selfhst/cdn directory/software.json",
        "fetched_at": "2026-04-26T05:38:19Z",
        "row_hash": "8c72502a68fe8aa61257ced963c75b855790cd795260dbac6e51c757f99e9d1d"
      }
    },
    {
      "reference": "snappymail",
      "name": "SnappyMail",
      "website": "snappymail.eu",
      "description": "Simple, modern, and fast web-based mail client",
      "repo_url": "github.com/the-djmaze/snappymail",
      "repo_key": "github.com/the-djmaze/snappymail",
      "stars": null,
      "forks": 0,
      "updated_at": "26",
      "license": null,
      "tags": [
        "Email"
      ],
      "readme_path": "knowledge/readmes/github.com__the-djmaze__snappymail.md",
      "readme_status": "not_modified",
      "provenance": {
        "source": "selfhst/cdn directory/software.json",
        "fetched_at": "2026-04-26T05:38:19Z",
        "row_hash": "61a42a3f4b3947d99864a7efdd6946a89234540e9461be550a00bc4a322cf3b0"
      }
    },
    {
      "reference": "snikket",
      "name": "Snikket",
      "website": "snikket.org/service/",
      "description": "Open source personal messaging service",
      "repo_url": "github.com/snikket-im/snikket-server",
      "repo_key": "github.com/snikket-im/snikket-server",
      "stars": null,
      "forks": 1,
      "updated_at": "22",
      "license": null,
      "tags": [
        "Messaging"
      ],
      "readme_path": "knowledge/readmes/github.com__snikket-im__snikket-server.md",
      "readme_status": "not_modified",
      "provenance": {
        "source": "selfhst/cdn directory/software.json",
        "fetched_at": "2026-04-26T05:38:19Z",
        "row_hash": "96cf31e286ad40bcedcfbd2df1f93e6360815b4e8a958971ca5ed7d7ea7faef8"
      }
    },
    {
      "reference": "snipe-it",
      "name": "Snipe-IT",
      "website": "snipeitapp.com",
      "description": "Asset management for IT operations",
      "repo_url": "github.com/grokability/snipe-it",
      "repo_key": "github.com/grokability/snipe-it",
      "stars": null,
      "forks": 0,
      "updated_at": "26",
      "license": null,
      "tags": [
        "Tracking"
      ],
      "readme_path": "knowledge/readmes/github.com__grokability__snipe-it.md",
      "readme_status": "not_modified",
      "provenance": {
        "source": "selfhst/cdn directory/software.json",
        "fetched_at": "2026-04-26T05:38:19Z",
        "row_hash": "ad32acf6a8060c6a7fa58847093fa3301c8e1f154a1bc2b504c5284745d8359d"
      }
    },
    {
      "reference": "snippets-library",
      "name": "Snippets Library",
      "website": "snippetslibrary.com/",
      "description": "Modern code snippet manager for devs",
      "repo_url": "github.com/cojocaru-david/snippetslibrary.com",
      "repo_key": "github.com/cojocaru-david/snippetslibrary.com",
      "stars": null,
      "forks": 8,
      "updated_at": "38",
      "license": null,
      "tags": [
        "Code Snippets"
      ],
      "readme_path": "knowledge/readmes/github.com__cojocaru-david__snippetslibrary.com.md",
      "readme_status": "not_modified",
      "provenance": {
        "source": "selfhst/cdn directory/software.json",
        "fetched_at": "2026-04-26T05:38:19Z",
        "row_hash": "e1571db51199b2bc8d86ab9a7287c51cf7a563a0d49c71bced3ec63dbfa10845"
      }
    },
    {
      "reference": "socialhome",
      "name": "Socialhome",
      "website": "gitlab.com/jaywink/socialhome",
      "description": "Federated personal profile with social networking",
      "repo_url": "gitlab.com/jaywink/socialhome",
      "repo_key": "gitlab.com/jaywink/socialhome",
      "stars": null,
      "forks": 0,
      "updated_at": "29",
      "license": null,
      "tags": [
        "ActivityPub / Fediverse"
      ],
      "readme_path": null,
      "readme_status": "error",
      "provenance": {
        "source": "selfhst/cdn directory/software.json",
        "fetched_at": "2026-04-26T05:38:19Z",
        "row_hash": "b4b61716e1733bbe435b9baa46d87be3abb487bb7c418c60a4eddd2b12a5f6f1"
      }
    },
    {
      "reference": "sofe",
      "name": "SoFE",
      "website": "github.com/chkpwd/sofe",
      "description": "Monitor non-filler episodes in Sonarr and generate Plex collections",
      "repo_url": "github.com/chkpwd/sofe",
      "repo_key": "github.com/chkpwd/sofe",
      "stars": null,
      "forks": 15,
      "updated_at": "29",
      "license": null,
      "tags": [
        "*arr",
        "Television"
      ],
      "readme_path": "knowledge/readmes/github.com__chkpwd__sofe.md",
      "readme_status": "not_modified",
      "provenance": {
        "source": "selfhst/cdn directory/software.json",
        "fetched_at": "2026-04-26T05:38:19Z",
        "row_hash": "dd297ed9dbba26abe51354df284da9a80e1514a693a8202f6d0a74ea26456ab9"
      }
    },
    {
      "reference": "soft-serve",
      "name": "Soft Serve",
      "website": "github.com/charmbracelet/soft-serve",
      "description": "Self-hostable git server for the command line",
      "repo_url": "github.com/charmbracelet/soft-serve",
      "repo_key": "github.com/charmbracelet/soft-serve",
      "stars": null,
      "forks": 15,
      "updated_at": "14",
      "license": null,
      "tags": [
        "Git"
      ],
      "readme_path": "knowledge/readmes/github.com__charmbracelet__soft-serve.md",
      "readme_status": "not_modified",
      "provenance": {
        "source": "selfhst/cdn directory/software.json",
        "fetched_at": "2026-04-26T05:38:19Z",
        "row_hash": "883fa6eb27a7e893edf78b4bd5e9f73e1c674c94f89e80ad90eebb4ae10a895c"
      }
    },
    {
      "reference": "solidinvoice",
      "name": "SolidInvoice",
      "website": "solidinvoice.co",
      "description": "Sophisticated invoicing application for small businesses",
      "repo_url": "github.com/SolidInvoice/SolidInvoice",
      "repo_key": "github.com/SolidInvoice/SolidInvoice",
      "stars": null,
      "forks": 15,
      "updated_at": "26",
      "license": null,
      "tags": [
        "Accounting"
      ],
      "readme_path": "knowledge/readmes/github.com__SolidInvoice__SolidInvoice.md",
      "readme_status": "not_modified",
      "provenance": {
        "source": "selfhst/cdn directory/software.json",
        "fetched_at": "2026-04-26T05:38:19Z",
        "row_hash": "80431833ca2c4a038a0d2422d91739abea5b660c3ed9a6c295da723c72d8bb01"
      }
    },
    {
      "reference": "solidtime",
      "name": "solidtime",
      "website": "www.solidtime.io",
      "description": "Modern open source time-tracking app",
      "repo_url": "github.com/solidtime-io/solidtime",
      "repo_key": "github.com/solidtime-io/solidtime",
      "stars": null,
      "forks": 0,
      "updated_at": "26",
      "license": null,
      "tags": [
        "Time Tracking",
        "Tracking"
      ],
      "readme_path": "knowledge/readmes/github.com__solidtime-io__solidtime.md",
      "readme_status": "not_modified",
      "provenance": {
        "source": "selfhst/cdn directory/software.json",
        "fetched_at": "2026-04-26T05:38:19Z",
        "row_hash": "ab1db9f3fe0fb5cb3a5af38147aa518eee79909da9d38ec0ab73ce450519adf1"
      }
    },
    {
      "reference": "sonarqube",
      "name": "SonarQube",
      "website": "http://www.sonarqube.org",
      "description": "Automated code quality and security analysis",
      "repo_url": "github.com/SonarSource/sonarqube",
      "repo_key": "github.com/SonarSource/sonarqube",
      "stars": null,
      "forks": 14,
      "updated_at": "19",
      "license": null,
      "tags": [
        "Development",
        "Development Environment"
      ],
      "readme_path": "knowledge/readmes/github.com__SonarSource__sonarqube.md",
      "readme_status": "not_modified",
      "provenance": {
        "source": "selfhst/cdn directory/software.json",
        "fetched_at": "2026-04-26T05:38:19Z",
        "row_hash": "efa7038744b483fd02f16a88052e4f984aa090fe4c7f582fd2db153c3c18bf37"
      }
    },
    {
      "reference": "sonarr",
      "name": "Sonarr",
      "website": "sonarr.tv",
      "description": "Smart PVR for newsgroup and bittorrent users",
      "repo_url": "github.com/Sonarr/Sonarr",
      "repo_key": "github.com/Sonarr/Sonarr",
      "stars": null,
      "forks": 11,
      "updated_at": "1",
      "license": null,
      "tags": [
        "*arr",
        "Media Management",
        "Television"
      ],
      "readme_path": "knowledge/readmes/github.com__Sonarr__Sonarr.md",
      "readme_status": "not_modified",
      "provenance": {
        "source": "selfhst/cdn directory/software.json",
        "fetched_at": "2026-04-26T05:38:19Z",
        "row_hash": "011ebc3d880705b3ec4df6bffadd7ce98a3b0285d275b0a60872cf419154e1df"
      }
    },
    {
      "reference": "sonashow",
      "name": "SonaShow",
      "website": "github.com/TheWicklowWolf/SonaShow",
      "description": "Web GUI for finding similar shows to selected Sonarr shows",
      "repo_url": "github.com/TheWicklowWolf/SonaShow",
      "repo_key": "github.com/TheWicklowWolf/SonaShow",
      "stars": null,
      "forks": 15,
      "updated_at": "29",
      "license": null,
      "tags": [
        "*arr",
        "Television"
      ],
      "readme_path": "knowledge/readmes/github.com__TheWicklowWolf__SonaShow.md",
      "readme_status": "not_modified",
      "provenance": {
        "source": "selfhst/cdn directory/software.json",
        "fetched_at": "2026-04-26T05:38:19Z",
        "row_hash": "e59c3306db557ea014890a4245733ba73fccd1d181df9f7e033d44b1c8ec9e79"
      }
    },
    {
      "reference": "sonobarr",
      "name": "Sonobarr",
      "website": "github.com/Dodelidoo-Labs/sonobarr",
      "description": "Music discovery for Lidarr users via Last.fm",
      "repo_url": "github.com/Dodelidoo-Labs/sonobarr",
      "repo_key": "github.com/Dodelidoo-Labs/sonobarr",
      "stars": null,
      "forks": 15,
      "updated_at": "29",
      "license": null,
      "tags": [
        "*arr",
        "Music"
      ],
      "readme_path": "knowledge/readmes/github.com__Dodelidoo-Labs__sonobarr.md",
      "readme_status": "not_modified",
      "provenance": {
        "source": "selfhst/cdn directory/software.json",
        "fetched_at": "2026-04-26T05:38:19Z",
        "row_hash": "5b6e5188532529bf51ba80b1489acbcc06e4f2093dcf53e310c029e57b81f78e"
      }
    },
    {
      "reference": "sortarr",
      "name": "Sortarr",
      "website": "github.com/Jaredharper1/Sortarr",
      "description": "Sonarr and Radarr library insights",
      "repo_url": "github.com/Jaredharper1/Sortarr",
      "repo_key": "github.com/Jaredharper1/Sortarr",
      "stars": null,
      "forks": 15,
      "updated_at": "29",
      "license": null,
      "tags": [
        "*arr"
      ],
      "readme_path": "knowledge/readmes/github.com__Jaredharper1__Sortarr.md",
      "readme_status": "not_modified",
      "provenance": {
        "source": "selfhst/cdn directory/software.json",
        "fetched_at": "2026-04-26T05:38:19Z",
        "row_hash": "c1c3734300bd637d27652e9977b0457c677bdcc52567b88201b4d2b36bab181e"
      }
    },
    {
      "reference": "sosse",
      "name": "Sosse",
      "website": "sosse.io",
      "description": "Selenium search engine for crawling and archiving",
      "repo_url": "github.com/biolds/sosse",
      "repo_key": "github.com/biolds/sosse",
      "stars": null,
      "forks": 0,
      "updated_at": "29",
      "license": null,
      "tags": [
        "Monitoring",
        "Search Engines"
      ],
      "readme_path": "knowledge/readmes/github.com__biolds__sosse.md",
      "readme_status": "not_modified",
      "provenance": {
        "source": "selfhst/cdn directory/software.json",
        "fetched_at": "2026-04-26T05:38:19Z",
        "row_hash": "8635bbe1013a5608b9ab148cbbf9fb45199317b88d20fa9d0dc96bd97f199cba"
      }
    },
    {
      "reference": "soulbeet",
      "name": "Soulbeet",
      "website": "github.com/terry90/soulbeet",
      "description": "Music downloads and discovery",
      "repo_url": "github.com/terry90/soulbeet",
      "repo_key": "github.com/terry90/soulbeet",
      "stars": null,
      "forks": 15,
      "updated_at": "31",
      "license": null,
      "tags": [
        "Downloads",
        "Music"
      ],
      "readme_path": "knowledge/readmes/github.com__terry90__soulbeet.md",
      "readme_status": "not_modified",
      "provenance": {
        "source": "selfhst/cdn directory/software.json",
        "fetched_at": "2026-04-26T05:38:19Z",
        "row_hash": "26c5c296c3b2e46bf1761fd973a802a7253761805cd603c7c6727b8b615ba35d"
      }
    },
    {
      "reference": "soulsync",
      "name": "SoulSync",
      "website": "ssync.net/",
      "description": "Automated music discovery and collection manager",
      "repo_url": "github.com/Nezreka/SoulSync",
      "repo_key": "github.com/Nezreka/SoulSync",
      "stars": null,
      "forks": 15,
      "updated_at": "29",
      "license": null,
      "tags": [
        "*arr",
        "Downloads",
        "Music"
      ],
      "readme_path": "knowledge/readmes/github.com__Nezreka__SoulSync.md",
      "readme_status": "not_modified",
      "provenance": {
        "source": "selfhst/cdn directory/software.json",
        "fetched_at": "2026-04-26T05:38:19Z",
        "row_hash": "be2aeec4291467fcb24e8933142ed5b31aa90e5f096ae21f0dde97c10091f1c8"
      }
    },
    {
      "reference": "sourcehut",
      "name": "SourceHut",
      "website": "sourcehut.org",
      "description": "Open source tools for project maintainers",
      "repo_url": "sr.ht/~sircmpwn/sourcehut",
      "repo_key": "sr.ht/~sircmpwn/sourcehut",
      "stars": null,
      "forks": null,
      "updated_at": "",
      "license": null,
      "tags": [
        "Development",
        "Git"
      ],
      "readme_path": null,
      "readme_status": "error",
      "provenance": {
        "source": "selfhst/cdn directory/software.json",
        "fetched_at": "2026-04-26T05:38:19Z",
        "row_hash": "be6946408973f454bb0d1f9b2148ce4250f33dbd56054915c515d593cfb3f92e"
      }
    },
    {
      "reference": "spacebar",
      "name": "Spacebar",
      "website": "spacebar.chat",
      "description": "Discord-compatible chat, voice, and video app",
      "repo_url": "github.com/spacebarchat/spacebarchat",
      "repo_key": "github.com/spacebarchat/spacebarchat",
      "stars": null,
      "forks": 0,
      "updated_at": "24",
      "license": null,
      "tags": [
        "Messaging",
        "Video Conferencing"
      ],
      "readme_path": "knowledge/readmes/github.com__spacebarchat__spacebarchat.md",
      "readme_status": "not_modified",
      "provenance": {
        "source": "selfhst/cdn directory/software.json",
        "fetched_at": "2026-04-26T05:38:19Z",
        "row_hash": "d423a1644dc78ff51562a93bd341969af7b4a90286e7d70a711f356b5863713f"
      }
    },
    {
      "reference": "spacepad",
      "name": "Spacepad",
      "website": "spacepad.io",
      "description": "Simple meeting room occupancy display",
      "repo_url": "github.com/magweter/spacepad",
      "repo_key": "github.com/magweter/spacepad",
      "stars": null,
      "forks": 8,
      "updated_at": "26",
      "license": null,
      "tags": [
        "Tracking"
      ],
      "readme_path": "knowledge/readmes/github.com__magweter__spacepad.md",
      "readme_status": "not_modified",
      "provenance": {
        "source": "selfhst/cdn directory/software.json",
        "fetched_at": "2026-04-26T05:38:19Z",
        "row_hash": "ebfed294ec194a20a8daa1c4f11ca59646e9d305b94073a8cb2a5ac9cd2c25f6"
      }
    },
    {
      "reference": "sparkybudget",
      "name": "SparkyBudget",
      "website": "github.com/CodeWithCJ/SparkyBudget",
      "description": "Personal finance management app",
      "repo_url": "github.com/CodeWithCJ/SparkyBudget",
      "repo_key": "github.com/CodeWithCJ/SparkyBudget",
      "stars": null,
      "forks": 8,
      "updated_at": "20",
      "license": null,
      "tags": [
        "Budgeting"
      ],
      "readme_path": "knowledge/readmes/github.com__CodeWithCJ__SparkyBudget.md",
      "readme_status": "not_modified",
      "provenance": {
        "source": "selfhst/cdn directory/software.json",
        "fetched_at": "2026-04-26T05:38:19Z",
        "row_hash": "1e53847dbf0de30a117379281b847df2896bcbd0d32eabed59ce45a65a4a62c5"
      }
    },
    {
      "reference": "sparkyfitness",
      "name": "SparkyFitness",
      "website": "codewithcj.github.io/SparkyFitness/",
      "description": "Comprehensive fitness tracking",
      "repo_url": "github.com/CodeWithCJ/SparkyFitness",
      "repo_key": "github.com/CodeWithCJ/SparkyFitness",
      "stars": null,
      "forks": 8,
      "updated_at": "38",
      "license": null,
      "tags": [
        "Fitness"
      ],
      "readme_path": "knowledge/readmes/github.com__CodeWithCJ__SparkyFitness.md",
      "readme_status": "not_modified",
      "provenance": {
        "source": "selfhst/cdn directory/software.json",
        "fetched_at": "2026-04-26T05:38:19Z",
        "row_hash": "ed55dc91cfb772eede034116f601999f303cfd13783e0803dcf865b35aa19058"
      }
    },
    {
      "reference": "speaches",
      "name": "Speaches",
      "website": "speaches.ai/",
      "description": "AI transcription, translation, and speed generation",
      "repo_url": "github.com/speaches-ai/speaches",
      "repo_key": "github.com/speaches-ai/speaches",
      "stars": null,
      "forks": 15,
      "updated_at": "29",
      "license": null,
      "tags": [
        "Artificial Intelligence",
        "Language",
        "Transcription"
      ],
      "readme_path": "knowledge/readmes/github.com__speaches-ai__speaches.md",
      "readme_status": "not_modified",
      "provenance": {
        "source": "selfhst/cdn directory/software.json",
        "fetched_at": "2026-04-26T05:38:19Z",
        "row_hash": "23b140b5799c04e324b627a0043f27a0badd923a8cf71ade6227429700c9dd9e"
      }
    },
    {
      "reference": "speakr",
      "name": "Speakr",
      "website": "github.com/murtaza-nasir/speakr",
      "description": "Intelligent note-taking for recordings and meetings",
      "repo_url": "github.com/murtaza-nasir/speakr",
      "repo_key": "github.com/murtaza-nasir/speakr",
      "stars": null,
      "forks": 0,
      "updated_at": "29",
      "license": null,
      "tags": [
        "Transcription"
      ],
      "readme_path": "knowledge/readmes/github.com__murtaza-nasir__speakr.md",
      "readme_status": "not_modified",
      "provenance": {
        "source": "selfhst/cdn directory/software.json",
        "fetched_at": "2026-04-26T05:38:19Z",
        "row_hash": "63bb1d1ec7ba8caba0a939b66f72070b142a0ce9b81c2b12b61517bd02c1fb11"
      }
    },
    {
      "reference": "specifically-clementines",
      "name": "Specifically Clementines",
      "website": "github.com/davideshay/groceries",
      "description": "Open source grocery lists",
      "repo_url": "github.com/davideshay/groceries",
      "repo_key": "github.com/davideshay/groceries",
      "stars": null,
      "forks": 15,
      "updated_at": "38",
      "license": null,
      "tags": [
        "Grocery Lists"
      ],
      "readme_path": "knowledge/readmes/github.com__davideshay__groceries.md",
      "readme_status": "not_modified",
      "provenance": {
        "source": "selfhst/cdn directory/software.json",
        "fetched_at": "2026-04-26T05:38:19Z",
        "row_hash": "84f31d867ab948a8ca62ba0074e50f1ef391a2402cb77e6c89c503a4b11b992b"
      }
    },
    {
      "reference": "speedtest-tracker",
      "name": "Speedtest Tracker",
      "website": "speedtest-tracker.dev/",
      "description": "Internet performance tracking application",
      "repo_url": "github.com/alexjustesen/speedtest-tracker",
      "repo_key": "github.com/alexjustesen/speedtest-tracker",
      "stars": null,
      "forks": 15,
      "updated_at": "26",
      "license": null,
      "tags": [
        "Speed Test"
      ],
      "readme_path": "knowledge/readmes/github.com__alexjustesen__speedtest-tracker.md",
      "readme_status": "not_modified",
      "provenance": {
        "source": "selfhst/cdn directory/software.json",
        "fetched_at": "2026-04-26T05:38:19Z",
        "row_hash": "7409fc6e3822c3c8f88de930b82cbd4751ddf02bbdfb6f3991196ac85a1371d2"
      }
    },
    {
      "reference": "spendspentspent",
      "name": "SpendSpentSpent",
      "website": "lamarios.github.io/SpendSpentSpent/",
      "description": "Easy-to-use expense tracker",
      "repo_url": "github.com/lamarios/SpendSpentSpent",
      "repo_key": "github.com/lamarios/SpendSpentSpent",
      "stars": null,
      "forks": 0,
      "updated_at": "6",
      "license": null,
      "tags": [
        "Budgeting",
        "Tracking"
      ],
      "readme_path": "knowledge/readmes/github.com__lamarios__SpendSpentSpent.md",
      "readme_status": "not_modified",
      "provenance": {
        "source": "selfhst/cdn directory/software.json",
        "fetched_at": "2026-04-26T05:38:19Z",
        "row_hash": "b56dead2176b9530871a34c5dec4740754d8ffdf543858549aafaa26d316c30f"
      }
    },
    {
      "reference": "spliit",
      "name": "Spliit",
      "website": "spliit.app",
      "description": "Share expenses with friends and family",
      "repo_url": "github.com/spliit-app/spliit",
      "repo_key": "github.com/spliit-app/spliit",
      "stars": null,
      "forks": 15,
      "updated_at": "38",
      "license": null,
      "tags": [
        "Budgeting"
      ],
      "readme_path": "knowledge/readmes/github.com__spliit-app__spliit.md",
      "readme_status": "not_modified",
      "provenance": {
        "source": "selfhst/cdn directory/software.json",
        "fetched_at": "2026-04-26T05:38:19Z",
        "row_hash": "ca08e226af78d7d5e41ef6565f3f66463092b2b0caee96a4991e67cde991b0c4"
      }
    },
    {
      "reference": "spoolman",
      "name": "Spoolman",
      "website": "github.com/Donkie/Spoolman",
      "description": "Inventory tracker for 3D printer filament spools",
      "repo_url": "github.com/Donkie/Spoolman",
      "repo_key": "github.com/Donkie/Spoolman",
      "stars": null,
      "forks": 15,
      "updated_at": "29",
      "license": null,
      "tags": [
        "3D Printing",
        "Inventory Management"
      ],
      "readme_path": "knowledge/readmes/github.com__Donkie__Spoolman.md",
      "readme_status": "not_modified",
      "provenance": {
        "source": "selfhst/cdn directory/software.json",
        "fetched_at": "2026-04-26T05:38:19Z",
        "row_hash": "312bf6ff9935ce3b1ed0458958f8c5fa0c7ace0bad313a9b4c44432dfa2cbe17"
      }
    },
    {
      "reference": "spooty",
      "name": "Spooty",
      "website": "github.com/Raiper34/spooty",
      "description": "Spotify track, playlist, and album downloader",
      "repo_url": "github.com/Raiper34/spooty",
      "repo_key": "github.com/Raiper34/spooty",
      "stars": null,
      "forks": 15,
      "updated_at": "38",
      "license": null,
      "tags": [
        "Downloads",
        "Music"
      ],
      "readme_path": "knowledge/readmes/github.com__Raiper34__spooty.md",
      "readme_status": "not_modified",
      "provenance": {
        "source": "selfhst/cdn directory/software.json",
        "fetched_at": "2026-04-26T05:38:19Z",
        "row_hash": "97ca7b3306322d4851e3460b7acb2495882400060f09dee20af73570debf7473"
      }
    },
    {
      "reference": "spotizerr",
      "name": "Spotizerr",
      "website": "lavaforge.org/spotizerr/spotizerr",
      "description": "Spotify music downloader",
      "repo_url": "lavaforge.org/spotizerr/spotizerr",
      "repo_key": "lavaforge.org/spotizerr/spotizerr",
      "stars": null,
      "forks": 11,
      "updated_at": "29",
      "license": null,
      "tags": [
        "Downloads",
        "Music"
      ],
      "readme_path": null,
      "readme_status": "error",
      "provenance": {
        "source": "selfhst/cdn directory/software.json",
        "fetched_at": "2026-04-26T05:38:19Z",
        "row_hash": "be35aca9745240d9baaf816fef4abd3a0bac40e22a4ff048d44f5a023bacc7f8"
      }
    },
    {
      "reference": "sprout-track",
      "name": "Sprout Track",
      "website": "www.sprout-track.com",
      "description": "Track baby diapers, feedings, naps, pumping, and other activities",
      "repo_url": "github.com/Oak-and-Sprout/sprout-track",
      "repo_key": "github.com/Oak-and-Sprout/sprout-track",
      "stars": null,
      "forks": 8,
      "updated_at": "38",
      "license": null,
      "tags": [
        "Tracking"
      ],
      "readme_path": "knowledge/readmes/github.com__Oak-and-Sprout__sprout-track.md",
      "readme_status": "not_modified",
      "provenance": {
        "source": "selfhst/cdn directory/software.json",
        "fetched_at": "2026-04-26T05:38:19Z",
        "row_hash": "0587fd2a67e23473cd4adace907af253932b58f6e63f20961d0f90d6af68d78a"
      }
    },
    {
      "reference": "squirrel-servers-manager",
      "name": "Squirrel Servers Manager",
      "website": "squirrelserversmanager.io/",
      "description": "User-friendly server configuration and management tool",
      "repo_url": "github.com/SquirrelCorporation/SquirrelServersManager",
      "repo_key": "github.com/SquirrelCorporation/SquirrelServersManager",
      "stars": null,
      "forks": 0,
      "updated_at": "38",
      "license": null,
      "tags": [
        "Docker",
        "Server Management"
      ],
      "readme_path": "knowledge/readmes/github.com__SquirrelCorporation__SquirrelServersManager.md",
      "readme_status": "not_modified",
      "provenance": {
        "source": "selfhst/cdn directory/software.json",
        "fetched_at": "2026-04-26T05:38:19Z",
        "row_hash": "61bf831eca4806b9445f5ea0e6984c7e089c6222e178b6f83d0be0119e24c1e1"
      }
    }
  ]
}