{
  "chunk": 6,
  "count": 50,
  "generated_at": "2026-04-26T05:45:46Z",
  "items": [
    {
      "repo_key": "github.com/Sharkord/sharkord",
      "repo_url": "github.com/Sharkord/sharkord",
      "host": "github.com",
      "owner": "Sharkord",
      "repo": "sharkord",
      "app_references": [
        "sharkord"
      ],
      "readme_status": "not_modified",
      "readme_path": "knowledge/readmes/github.com__Sharkord__sharkord.md",
      "readme_download_url": null,
      "readme_sha256": "a8cb7295499f565841fb1444db972e8c8bbeaf73887d4262de4ffac95f515912",
      "error": null
    },
    {
      "repo_key": "github.com/SheetAble/SheetAble",
      "repo_url": "github.com/SheetAble/SheetAble",
      "host": "github.com",
      "owner": "SheetAble",
      "repo": "SheetAble",
      "app_references": [
        "sheetable"
      ],
      "readme_status": "not_modified",
      "readme_path": "knowledge/readmes/github.com__SheetAble__SheetAble.md",
      "readme_download_url": null,
      "readme_sha256": "465b250733a28f91f10630d557879fbf6f4bca1ea18c2c9e9c1ee95031a496bb",
      "error": null
    },
    {
      "repo_key": "github.com/SigNoz/signoz",
      "repo_url": "github.com/SigNoz/signoz",
      "host": "github.com",
      "owner": "SigNoz",
      "repo": "signoz",
      "app_references": [
        "signoz"
      ],
      "readme_status": "not_modified",
      "readme_path": "knowledge/readmes/github.com__SigNoz__signoz.md",
      "readme_download_url": null,
      "readme_sha256": "9927507efc10566752a49bc8782d96895ec5b7e44d85d4982d0cf8a4766a60e4",
      "error": null
    },
    {
      "repo_key": "github.com/Simounet/flox",
      "repo_url": "github.com/Simounet/flox",
      "host": "github.com",
      "owner": "Simounet",
      "repo": "flox",
      "app_references": [
        "flox"
      ],
      "readme_status": "not_modified",
      "readme_path": "knowledge/readmes/github.com__Simounet__flox.md",
      "readme_download_url": null,
      "readme_sha256": "4aa6ac089d1dc209c98991712d96196f466ca4f4f25e56d766af615dbd9e8506",
      "error": null
    },
    {
      "repo_key": "github.com/SimpleHomelab/Deployrr",
      "repo_url": "github.com/SimpleHomelab/Deployrr",
      "host": "github.com",
      "owner": "SimpleHomelab",
      "repo": "Deployrr",
      "app_references": [
        "deployrr"
      ],
      "readme_status": "not_modified",
      "readme_path": "knowledge/readmes/github.com__SimpleHomelab__Deployrr.md",
      "readme_download_url": null,
      "readme_sha256": "0ed5535cb9f37368ddba787b817b147b50ce8371ba5825b38228836e7faa147d",
      "error": null
    },
    {
      "repo_key": "github.com/SinTan1729/chhoto-url",
      "repo_url": "github.com/SinTan1729/chhoto-url",
      "host": "github.com",
      "owner": "SinTan1729",
      "repo": "chhoto-url",
      "app_references": [
        "chhoto-url"
      ],
      "readme_status": "not_modified",
      "readme_path": "knowledge/readmes/github.com__SinTan1729__chhoto-url.md",
      "readme_download_url": null,
      "readme_sha256": "68a24a9b93370c719fd6194f8d548fafaf109f9273ee8bce4129e19761884526",
      "error": null
    },
    {
      "repo_key": "github.com/Smaug6739/Alexandrie",
      "repo_url": "github.com/Smaug6739/Alexandrie",
      "host": "github.com",
      "owner": "Smaug6739",
      "repo": "Alexandrie",
      "app_references": [
        "alexandrie"
      ],
      "readme_status": "not_modified",
      "readme_path": "knowledge/readmes/github.com__Smaug6739__Alexandrie.md",
      "readme_download_url": null,
      "readme_sha256": "4324b46373b40b5fe55a48e61b7f1040a5a9a714e6300356195fcf9e6b2b3f51",
      "error": null
    },
    {
      "repo_key": "github.com/SmilyOrg/photofield",
      "repo_url": "github.com/SmilyOrg/photofield",
      "host": "github.com",
      "owner": "SmilyOrg",
      "repo": "photofield",
      "app_references": [
        "photofield"
      ],
      "readme_status": "not_modified",
      "readme_path": "knowledge/readmes/github.com__SmilyOrg__photofield.md",
      "readme_download_url": null,
      "readme_sha256": "a78a7902a0a5c82718c808c7ab2b8c26f8f2c3b9a8925bd5861e3a9d0c9b02ef",
      "error": null
    },
    {
      "repo_key": "github.com/SnapDrop/snapdrop",
      "repo_url": "github.com/SnapDrop/snapdrop",
      "host": "github.com",
      "owner": "SnapDrop",
      "repo": "snapdrop",
      "app_references": [
        "snapdrop"
      ],
      "readme_status": "not_modified",
      "readme_path": "knowledge/readmes/github.com__SnapDrop__snapdrop.md",
      "readme_download_url": null,
      "readme_sha256": "90990ea35e441163502d4255acfbf8bdc0f1c25796ee0bb4b2192198d10abbb4",
      "error": null
    },
    {
      "repo_key": "github.com/Snouzy/workout-cool",
      "repo_url": "github.com/Snouzy/workout-cool",
      "host": "github.com",
      "owner": "Snouzy",
      "repo": "workout-cool",
      "app_references": [
        "workout-cool"
      ],
      "readme_status": "not_modified",
      "readme_path": "knowledge/readmes/github.com__Snouzy__workout-cool.md",
      "readme_download_url": null,
      "readme_sha256": "0d267b08ea412ceddfcdcd1a94a8f427bfb5f8a51f57ca8ea0b48073eb050b9d",
      "error": null
    },
    {
      "repo_key": "github.com/SolidInvoice/SolidInvoice",
      "repo_url": "github.com/SolidInvoice/SolidInvoice",
      "host": "github.com",
      "owner": "SolidInvoice",
      "repo": "SolidInvoice",
      "app_references": [
        "solidinvoice"
      ],
      "readme_status": "not_modified",
      "readme_path": "knowledge/readmes/github.com__SolidInvoice__SolidInvoice.md",
      "readme_download_url": null,
      "readme_sha256": "9c5febeac1e343faa5dcdbc3e81ebd382494b5d4f9d0189d20e6452a7440f82a",
      "error": null
    },
    {
      "repo_key": "github.com/SonarSource/sonarqube",
      "repo_url": "github.com/SonarSource/sonarqube",
      "host": "github.com",
      "owner": "SonarSource",
      "repo": "sonarqube",
      "app_references": [
        "sonarqube"
      ],
      "readme_status": "not_modified",
      "readme_path": "knowledge/readmes/github.com__SonarSource__sonarqube.md",
      "readme_download_url": null,
      "readme_sha256": "ac806386b6cd9c0fff1a7749d964352d155539ef6fa5e93fbd8ec4bf98539397",
      "error": null
    },
    {
      "repo_key": "github.com/Sonarr/Sonarr",
      "repo_url": "github.com/Sonarr/Sonarr",
      "host": "github.com",
      "owner": "Sonarr",
      "repo": "Sonarr",
      "app_references": [
        "sonarr"
      ],
      "readme_status": "not_modified",
      "readme_path": "knowledge/readmes/github.com__Sonarr__Sonarr.md",
      "readme_download_url": null,
      "readme_sha256": "564f70398f6741ad94a6073a5709ab6a01bc7c209c4e4b306f2233404f576bbe",
      "error": null
    },
    {
      "repo_key": "github.com/Southclaws/storyden",
      "repo_url": "github.com/Southclaws/storyden",
      "host": "github.com",
      "owner": "Southclaws",
      "repo": "storyden",
      "app_references": [
        "storyden"
      ],
      "readme_status": "not_modified",
      "readme_path": "knowledge/readmes/github.com__Southclaws__storyden.md",
      "readme_download_url": null,
      "readme_sha256": "1523672d940ca48c8c3da8d3fed13961b4dc184674717a2fc08626a226ba0f7d",
      "error": null
    },
    {
      "repo_key": "github.com/SquirrelCorporation/SquirrelServersManager",
      "repo_url": "github.com/SquirrelCorporation/SquirrelServersManager",
      "host": "github.com",
      "owner": "SquirrelCorporation",
      "repo": "SquirrelServersManager",
      "app_references": [
        "squirrel-servers-manager"
      ],
      "readme_status": "not_modified",
      "readme_path": "knowledge/readmes/github.com__SquirrelCorporation__SquirrelServersManager.md",
      "readme_download_url": null,
      "readme_sha256": "23bf5ea2550ca2af208bdf55230a5789292547d19c389c9f3db3ecaad24b7798",
      "error": null
    },
    {
      "repo_key": "github.com/StarFleetCPTN/GoMFT",
      "repo_url": "github.com/StarFleetCPTN/GoMFT",
      "host": "github.com",
      "owner": "StarFleetCPTN",
      "repo": "GoMFT",
      "app_references": [
        "gomft"
      ],
      "readme_status": "not_modified",
      "readme_path": "knowledge/readmes/github.com__StarFleetCPTN__GoMFT.md",
      "readme_download_url": null,
      "readme_sha256": "09d1e2375bce9288608f05804d00f161ba2ba273410316aae420235750f8b9d1",
      "error": null
    },
    {
      "repo_key": "github.com/Steam-Headless/docker-steam-headless",
      "repo_url": "github.com/Steam-Headless/docker-steam-headless",
      "host": "github.com",
      "owner": "Steam-Headless",
      "repo": "docker-steam-headless",
      "app_references": [
        "steam-headless"
      ],
      "readme_status": "not_modified",
      "readme_path": "knowledge/readmes/github.com__Steam-Headless__docker-steam-headless.md",
      "readme_download_url": null,
      "readme_sha256": "9d4e1fdb729d44762b984900c6eccdd8e9bbf3b49caa504d6987666d7b6f01e4",
      "error": null
    },
    {
      "repo_key": "github.com/Stirling-Tools/Stirling-PDF",
      "repo_url": "github.com/Stirling-Tools/Stirling-PDF",
      "host": "github.com",
      "owner": "Stirling-Tools",
      "repo": "Stirling-PDF",
      "app_references": [
        "stirling-pdf"
      ],
      "readme_status": "not_modified",
      "readme_path": "knowledge/readmes/github.com__Stirling-Tools__Stirling-PDF.md",
      "readme_download_url": null,
      "readme_sha256": "2c25f497c53e4128584b2b7ed23bca1ace3edbb4831eb31de67d4bcf60fb7978",
      "error": null
    },
    {
      "repo_key": "github.com/StuffAnThings/qbit_manage",
      "repo_url": "github.com/StuffAnThings/qbit_manage",
      "host": "github.com",
      "owner": "StuffAnThings",
      "repo": "qbit_manage",
      "app_references": [
        "qbit-manage"
      ],
      "readme_status": "not_modified",
      "readme_path": "knowledge/readmes/github.com__StuffAnThings__qbit_manage.md",
      "readme_download_url": null,
      "readme_sha256": "9ea5a542eb1018b59f293373eb1c52966542f7e150aa0dd9c6863e845ccbaa91",
      "error": null
    },
    {
      "repo_key": "github.com/SubleXBle/Fail2Ban-Report",
      "repo_url": "github.com/SubleXBle/Fail2Ban-Report",
      "host": "github.com",
      "owner": "SubleXBle",
      "repo": "Fail2Ban-Report",
      "app_references": [
        "fail2ban-report"
      ],
      "readme_status": "not_modified",
      "readme_path": "knowledge/readmes/github.com__SubleXBle__Fail2Ban-Report.md",
      "readme_download_url": null,
      "readme_sha256": "2a948b5d9daf995f1329a1655e3162de073d7496a1771ecf1211308f643cbe9a",
      "error": null
    },
    {
      "repo_key": "github.com/Svedrin/meshping",
      "repo_url": "github.com/Svedrin/meshping",
      "host": "github.com",
      "owner": "Svedrin",
      "repo": "meshping",
      "app_references": [
        "meshping"
      ],
      "readme_status": "not_modified",
      "readme_path": "knowledge/readmes/github.com__Svedrin__meshping.md",
      "readme_download_url": null,
      "readme_sha256": "59737e5e137600e47cdbc205af1ff43dece70ba7bab3435d5e63136841461dd1",
      "error": null
    },
    {
      "repo_key": "github.com/Swetrix/swetrix",
      "repo_url": "github.com/Swetrix/swetrix",
      "host": "github.com",
      "owner": "Swetrix",
      "repo": "swetrix",
      "app_references": [
        "swetrix"
      ],
      "readme_status": "not_modified",
      "readme_path": "knowledge/readmes/github.com__Swetrix__swetrix.md",
      "readme_download_url": null,
      "readme_sha256": "9ebc8dbb559e2d3f6038dd11ba3eacd71913ec67f557412855606c7520b715a7",
      "error": null
    },
    {
      "repo_key": "github.com/Sync-in/server",
      "repo_url": "github.com/Sync-in/server",
      "host": "github.com",
      "owner": "Sync-in",
      "repo": "server",
      "app_references": [
        "sync-in"
      ],
      "readme_status": "not_modified",
      "readme_path": "knowledge/readmes/github.com__Sync-in__server.md",
      "readme_download_url": null,
      "readme_sha256": "1c178239d4aabc4169e69fe31fb0cdb09cf972c3f295dc9e92d2d731745fb3e7",
      "error": null
    },
    {
      "repo_key": "github.com/TM9657/flow-like",
      "repo_url": "github.com/TM9657/flow-like",
      "host": "github.com",
      "owner": "TM9657",
      "repo": "flow-like",
      "app_references": [
        "flow-like"
      ],
      "readme_status": "not_modified",
      "readme_path": "knowledge/readmes/github.com__TM9657__flow-like.md",
      "readme_download_url": null,
      "readme_sha256": "e92b1c31df18f1210f51e2d1feb2e347b6c9f9ec93401474eebe7bcf56726ab5",
      "error": null
    },
    {
      "repo_key": "github.com/TYPO3/typo3",
      "repo_url": "github.com/TYPO3/typo3",
      "host": "github.com",
      "owner": "TYPO3",
      "repo": "typo3",
      "app_references": [
        "typo3"
      ],
      "readme_status": "not_modified",
      "readme_path": "knowledge/readmes/github.com__TYPO3__typo3.md",
      "readme_download_url": null,
      "readme_sha256": "6ba1f12a9d41e5118ca58949d457014c32a3fb2e2ac65f4633e8b8fd93d10bf5",
      "error": null
    },
    {
      "repo_key": "github.com/TandoorRecipes/recipes",
      "repo_url": "github.com/TandoorRecipes/recipes",
      "host": "github.com",
      "owner": "TandoorRecipes",
      "repo": "recipes",
      "app_references": [
        "tandoor-recipes"
      ],
      "readme_status": "not_modified",
      "readme_path": "knowledge/readmes/github.com__TandoorRecipes__recipes.md",
      "readme_download_url": null,
      "readme_sha256": "2dec8a6a224dcf4645890a7ec0c3af6cca37b89ce3e9def51b463861a3f95683",
      "error": null
    },
    {
      "repo_key": "github.com/Tanq16/ExpenseOwl",
      "repo_url": "github.com/Tanq16/ExpenseOwl",
      "host": "github.com",
      "owner": "Tanq16",
      "repo": "ExpenseOwl",
      "app_references": [
        "expenseowl"
      ],
      "readme_status": "not_modified",
      "readme_path": "knowledge/readmes/github.com__Tanq16__ExpenseOwl.md",
      "readme_download_url": null,
      "readme_sha256": "82be809c754bdaccc52868ed282e94d4d0a27d525d80126940cfe3099b602701",
      "error": null
    },
    {
      "repo_key": "github.com/TasmoAdmin/TasmoAdmin",
      "repo_url": "github.com/TasmoAdmin/TasmoAdmin",
      "host": "github.com",
      "owner": "TasmoAdmin",
      "repo": "TasmoAdmin",
      "app_references": [
        "tasmoadmin"
      ],
      "readme_status": "not_modified",
      "readme_path": "knowledge/readmes/github.com__TasmoAdmin__TasmoAdmin.md",
      "readme_download_url": null,
      "readme_sha256": "177e7fe0b8a7cb49de0f8cba63cf300ae7e7a91aa0392fe7c20c840714772c22",
      "error": null
    },
    {
      "repo_key": "github.com/Tautulli/Tautulli",
      "repo_url": "github.com/Tautulli/Tautulli",
      "host": "github.com",
      "owner": "Tautulli",
      "repo": "Tautulli",
      "app_references": [
        "tautulli"
      ],
      "readme_status": "not_modified",
      "readme_path": "knowledge/readmes/github.com__Tautulli__Tautulli.md",
      "readme_download_url": null,
      "readme_sha256": "8cde10071f57e46949e1d94e47cb806ea1f28024dea7ff3fd4d695923f969e02",
      "error": null
    },
    {
      "repo_key": "github.com/TeamPiped/Piped",
      "repo_url": "github.com/TeamPiped/Piped",
      "host": "github.com",
      "owner": "TeamPiped",
      "repo": "Piped",
      "app_references": [
        "piped"
      ],
      "readme_status": "not_modified",
      "readme_path": "knowledge/readmes/github.com__TeamPiped__Piped.md",
      "readme_download_url": null,
      "readme_sha256": "17a3861bc81306f52130807e70b8b3ac90bb33dfd2000cdd6a3a402a5701b98b",
      "error": null
    },
    {
      "repo_key": "github.com/TechnitiumSoftware/DnsServer",
      "repo_url": "github.com/TechnitiumSoftware/DnsServer",
      "host": "github.com",
      "owner": "TechnitiumSoftware",
      "repo": "DnsServer",
      "app_references": [
        "technitium"
      ],
      "readme_status": "ok",
      "readme_path": "knowledge/readmes/github.com__TechnitiumSoftware__DnsServer.md",
      "readme_download_url": "https://raw.githubusercontent.com/TechnitiumSoftware/DnsServer/master/README.md",
      "readme_sha256": "9e42978c130841e0f7fc09b23dc9da893beff4e2aae4e80b608fec33157663b2",
      "error": null
    },
    {
      "repo_key": "github.com/Tecnativa/docker-socket-proxy",
      "repo_url": "github.com/Tecnativa/docker-socket-proxy",
      "host": "github.com",
      "owner": "Tecnativa",
      "repo": "docker-socket-proxy",
      "app_references": [
        "docker-socket-proxy"
      ],
      "readme_status": "not_modified",
      "readme_path": "knowledge/readmes/github.com__Tecnativa__docker-socket-proxy.md",
      "readme_download_url": null,
      "readme_sha256": "ea2158e1cd235aa5167c6e4343fcf3444c22655c25f64134c7a437a05ca53832",
      "error": null
    },
    {
      "repo_key": "github.com/Termix-SSH/Termix",
      "repo_url": "github.com/Termix-SSH/Termix",
      "host": "github.com",
      "owner": "Termix-SSH",
      "repo": "Termix",
      "app_references": [
        "termix"
      ],
      "readme_status": "ok",
      "readme_path": "knowledge/readmes/github.com__Termix-SSH__Termix.md",
      "readme_download_url": "https://raw.githubusercontent.com/Termix-SSH/Termix/main/README.md",
      "readme_sha256": "444edbd0150b0333e2b354a8b87b6c1be32a8e2bccd9e863f380813ffd807a0f",
      "error": null
    },
    {
      "repo_key": "github.com/TheAxelander/OpenBudgeteer",
      "repo_url": "github.com/TheAxelander/OpenBudgeteer",
      "host": "github.com",
      "owner": "TheAxelander",
      "repo": "OpenBudgeteer",
      "app_references": [
        "openbudgeteer"
      ],
      "readme_status": "not_modified",
      "readme_path": "knowledge/readmes/github.com__TheAxelander__OpenBudgeteer.md",
      "readme_download_url": null,
      "readme_sha256": "c0afe6af5036c2b29e881c7e88d1106aafdc29c0bf49ad7e65df80a1c90aecf7",
      "error": null
    },
    {
      "repo_key": "github.com/TheBigRoomXXL/tinyfeed",
      "repo_url": "github.com/TheBigRoomXXL/tinyfeed",
      "host": "github.com",
      "owner": "TheBigRoomXXL",
      "repo": "tinyfeed",
      "app_references": [
        "tinyfeed"
      ],
      "readme_status": "not_modified",
      "readme_path": "knowledge/readmes/github.com__TheBigRoomXXL__tinyfeed.md",
      "readme_download_url": null,
      "readme_sha256": "6735250c779f2d72526b5791d1756870c2ef3b10e75a7b08963a2c2a3c45c008",
      "error": null
    },
    {
      "repo_key": "github.com/TheNickOfTime/handbrake-web",
      "repo_url": "github.com/TheNickOfTime/handbrake-web",
      "host": "github.com",
      "owner": "TheNickOfTime",
      "repo": "handbrake-web",
      "app_references": [
        "handbrake-web"
      ],
      "readme_status": "not_modified",
      "readme_path": "knowledge/readmes/github.com__TheNickOfTime__handbrake-web.md",
      "readme_download_url": null,
      "readme_sha256": "65b67b11911b01ab0f3bb367bacf9143c14947e5a182e9615e812eeeffb32e31",
      "error": null
    },
    {
      "repo_key": "github.com/TheSpaghettiDetective/obico-server",
      "repo_url": "github.com/TheSpaghettiDetective/obico-server",
      "host": "github.com",
      "owner": "TheSpaghettiDetective",
      "repo": "obico-server",
      "app_references": [
        "obico"
      ],
      "readme_status": "not_modified",
      "readme_path": "knowledge/readmes/github.com__TheSpaghettiDetective__obico-server.md",
      "readme_download_url": null,
      "readme_sha256": "57d6536097f783ea93b1c6717a36dd92e35dd22d02141121c0e26ba390254cd4",
      "error": null
    },
    {
      "repo_key": "github.com/TheWicklowWolf/Lidify",
      "repo_url": "github.com/TheWicklowWolf/Lidify",
      "host": "github.com",
      "owner": "TheWicklowWolf",
      "repo": "Lidify",
      "app_references": [
        "lidify"
      ],
      "readme_status": "not_modified",
      "readme_path": "knowledge/readmes/github.com__TheWicklowWolf__Lidify.md",
      "readme_download_url": null,
      "readme_sha256": "38d523d4be3bb9f9348f9dc47606d64e48e932ad535f948de5a62a0ff0500802",
      "error": null
    },
    {
      "repo_key": "github.com/TheWicklowWolf/RadaRec",
      "repo_url": "github.com/TheWicklowWolf/RadaRec",
      "host": "github.com",
      "owner": "TheWicklowWolf",
      "repo": "RadaRec",
      "app_references": [
        "radarec"
      ],
      "readme_status": "not_modified",
      "readme_path": "knowledge/readmes/github.com__TheWicklowWolf__RadaRec.md",
      "readme_download_url": null,
      "readme_sha256": "b80f5a59ea4f24871dd451d63a543056753dc386ba6ba27c61c3716a16580553",
      "error": null
    },
    {
      "repo_key": "github.com/TheWicklowWolf/SonaShow",
      "repo_url": "github.com/TheWicklowWolf/SonaShow",
      "host": "github.com",
      "owner": "TheWicklowWolf",
      "repo": "SonaShow",
      "app_references": [
        "sonashow"
      ],
      "readme_status": "not_modified",
      "readme_path": "knowledge/readmes/github.com__TheWicklowWolf__SonaShow.md",
      "readme_download_url": null,
      "readme_sha256": "9a84b380646796d9bcb02432d147a75fb9e6220371eda4db56c8ac5ac2a269b6",
      "error": null
    },
    {
      "repo_key": "github.com/TiddlyWiki/TiddlyWiki5",
      "repo_url": "github.com/TiddlyWiki/TiddlyWiki5",
      "host": "github.com",
      "owner": "TiddlyWiki",
      "repo": "TiddlyWiki5",
      "app_references": [
        "tiddlywiki"
      ],
      "readme_status": "ok",
      "readme_path": "knowledge/readmes/github.com__TiddlyWiki__TiddlyWiki5.md",
      "readme_download_url": "https://raw.githubusercontent.com/TiddlyWiki/TiddlyWiki5/master/readme.md",
      "readme_sha256": "679f7bbd71f575f22f7c48d37911eb4fc8d1abb22189fde56445e0616d8ea482",
      "error": null
    },
    {
      "repo_key": "github.com/Tiendil/feeds.fun",
      "repo_url": "github.com/Tiendil/feeds.fun",
      "host": "github.com",
      "owner": "Tiendil",
      "repo": "feeds.fun",
      "app_references": [
        "feeds-fun"
      ],
      "readme_status": "not_modified",
      "readme_path": "knowledge/readmes/github.com__Tiendil__feeds.fun.md",
      "readme_download_url": null,
      "readme_sha256": "7660f3bf19b65f4d3d86e42f018a5438b12c0b110a893e993fed620bbb43a91c",
      "error": null
    },
    {
      "repo_key": "github.com/TimWitzdam/GitSave",
      "repo_url": "github.com/TimWitzdam/GitSave",
      "host": "github.com",
      "owner": "TimWitzdam",
      "repo": "GitSave",
      "app_references": [
        "gitsave"
      ],
      "readme_status": "not_modified",
      "readme_path": "knowledge/readmes/github.com__TimWitzdam__GitSave.md",
      "readme_download_url": null,
      "readme_sha256": "b7293a511cf6a6a4e4e8b2f5954561ba6f87245887466cc5ed12c998f3f45030",
      "error": null
    },
    {
      "repo_key": "github.com/TobiasMarschner/ferrishare",
      "repo_url": "github.com/TobiasMarschner/ferrishare",
      "host": "github.com",
      "owner": "TobiasMarschner",
      "repo": "ferrishare",
      "app_references": [
        "ferrishare"
      ],
      "readme_status": "not_modified",
      "readme_path": "knowledge/readmes/github.com__TobiasMarschner__ferrishare.md",
      "readme_download_url": null,
      "readme_sha256": "b3908cfef345902bf3ac81559b6363124d2b7b358a24945375e678c5d0fb1456",
      "error": null
    },
    {
      "repo_key": "github.com/TomBursch/kitchenowl",
      "repo_url": "github.com/TomBursch/kitchenowl",
      "host": "github.com",
      "owner": "TomBursch",
      "repo": "kitchenowl",
      "app_references": [
        "kitchenowl"
      ],
      "readme_status": "not_modified",
      "readme_path": "knowledge/readmes/github.com__TomBursch__kitchenowl.md",
      "readme_download_url": null,
      "readme_sha256": "f9dedaa5f945914ec5d191e781568b785ffdbf833eef1e4f8893375595d04fac",
      "error": null
    },
    {
      "repo_key": "github.com/ToolJet/ToolJet",
      "repo_url": "github.com/ToolJet/ToolJet",
      "host": "github.com",
      "owner": "ToolJet",
      "repo": "ToolJet",
      "app_references": [
        "tooljet"
      ],
      "readme_status": "not_modified",
      "readme_path": "knowledge/readmes/github.com__ToolJet__ToolJet.md",
      "readme_download_url": null,
      "readme_sha256": "077435e805ebefcad2aae589817c2a44ff4a8011ddb4346cde49e0b3dcd2bd7d",
      "error": null
    },
    {
      "repo_key": "github.com/TriliumNext/Trilium",
      "repo_url": "github.com/TriliumNext/Trilium",
      "host": "github.com",
      "owner": "TriliumNext",
      "repo": "Trilium",
      "app_references": [
        "trilium-notes"
      ],
      "readme_status": "not_modified",
      "readme_path": "knowledge/readmes/github.com__TriliumNext__Trilium.md",
      "readme_download_url": null,
      "readme_sha256": "2594223ea1274b21003b06ed97e07dd8bc646bc15db79101b388ce53ef306ca0",
      "error": null
    },
    {
      "repo_key": "github.com/Trugamr/wol",
      "repo_url": "github.com/Trugamr/wol",
      "host": "github.com",
      "owner": "Trugamr",
      "repo": "wol",
      "app_references": [
        "wol"
      ],
      "readme_status": "not_modified",
      "readme_path": "knowledge/readmes/github.com__Trugamr__wol.md",
      "readme_download_url": null,
      "readme_sha256": "97cadb7b511408a1f437240ce35e1d8950fc0bb6fb1009971196b9ecf3d09951",
      "error": null
    },
    {
      "repo_key": "github.com/TryGhost/Ghost",
      "repo_url": "github.com/TryGhost/Ghost",
      "host": "github.com",
      "owner": "TryGhost",
      "repo": "Ghost",
      "app_references": [
        "ghost"
      ],
      "readme_status": "not_modified",
      "readme_path": "knowledge/readmes/github.com__TryGhost__Ghost.md",
      "readme_download_url": null,
      "readme_sha256": "a53cfa4b62be7d1b22587c1452788470cd49db2581904c9035cffa5dc867f168",
      "error": null
    },
    {
      "repo_key": "github.com/TwiN/gatus",
      "repo_url": "github.com/TwiN/gatus",
      "host": "github.com",
      "owner": "TwiN",
      "repo": "gatus",
      "app_references": [
        "gatus"
      ],
      "readme_status": "ok",
      "readme_path": "knowledge/readmes/github.com__TwiN__gatus.md",
      "readme_download_url": "https://raw.githubusercontent.com/TwiN/gatus/master/README.md",
      "readme_sha256": "bf49cebd39131ba12a700dd8e88d940b12176682de4986119124b4efd9b2a7f8",
      "error": null
    }
  ]
}